Workbook

Sheet README
B2: RetailQE - Test Case List & Requirements Traceability Matrix
B3: Lewis Retail Group - Retail Delivery Module (Quality Engineering Capstone)
B5: Sheets in this workbook
B6: Test Cases | C6: All 100 layer tests (40 Cypress, 40 Postman, 20 SQL) plus the 5 E2E scenarios, with IDs in the T-LAYER-FEATURE-### format.
B7: E2E Steps | C7: Step-by-step detail for the 5 end-to-end scenarios (each step is tagged UI, API or SQL and mapped to acceptance criteria).
B8: RTM | C8: Requirements Traceability Matrix: every acceptance criterion of FR-001 to FR-007 mapped to its tests. Counts, coverage and results are formulas that read from 'Test Cases'.
B9: Coverage Summary | C9: Counts per layer and feature against the brief's targets, pass rates against the exit criteria, and FR/AC coverage. All formulas.
B11: What to edit (yellow columns on 'Test Cases')
B12: Automation Status | C12: Planned / In Progress / Automated / Manual (drop-down).
B13: Execution Status | C13: Not Run / Pass / Fail / Blocked / Skipped (drop-down). The RTM and Coverage Summary update automatically from this column.
B14: Executed By / Date | C14: Tester name and run date, e.g. 'Uzair' and 2026-11-03.
B15: Defect ID | C15: JIRA defect key, e.g. RQE-42. Separate several with a semicolon. Copy the IDs into the RTM 'Defect IDs' column as well.
B16: Evidence Link | C16: Path or link to the proof, e.g. reports/cypress/T-UI-PAY-001.png or a JIRA attachment link.
B17: JIRA Story | C17: Story/epic key the test traces to, e.g. RQE-7.
B18: RTM (yellow columns) | C18: Defect IDs and JIRA Story/Epic for each acceptance criterion. Everything else on the RTM is calculated.
B20: Assumptions and things to confirm
B21: Written before the SUT | C21: These tests were written from the capstone brief only; the application, API and database have not been seen yet. Selectors, endpoints, status codes, table names and error messages are provisional and should be confirmed against the real system and its Swagger docs.
B22: Table names | C22: SQL tests use generic table names (Orders, OrderItems, Payments, Refunds, Shipments, Inventory, InventoryLedger, AuditLog, NotificationLog, ProofOfDelivery). Rename to match the real schema.
B23: E2E step count | C23: The brief says E2E scenarios need >=10 steps each, but lists 'Payment Failure & Retry' as 5 steps. All 5 scenarios here have 11-13 steps; the 5-step core of the payment scenario is steps 2-6.
B24: Counts | C24: The brief says 100 tests 'excluding E2E steps'. The 5 E2E scenarios are counted separately, so the workbook has 105 rows.
B25: FR-006 at API level | C25: Section 2.2 has no Dashboard API category, so FR-006 is covered by API-ORD-010 (history, pagination, filters) and API-ERR-004 (profile and saved addresses). Move ERR-004 into its own folder if your facilitator prefers.
B26: Cross-browser | C26: Cypress supports Chrome, Firefox and Edge. Cross-browser tests T-UI-XBR-001 to 003 re-run the login flow; 004-005 re-run the totals flow; 006 checks two desktop resolutions.
B27: Session expiry | C27: T-UI-AUTH-004 uses cy.clock. If the app enforces expiry only on the server, shorten the token lifetime in the test environment instead.
B28: Out of scope | C28: Performance, security penetration, mobile apps, building the retail system and DevOps are excluded per the brief.
B30: Colour key
B31: Yellow header/cell | C31: Cells for you to fill in.
B32: Blue text | C32: Cells for you to fill in (yellow fill). Blue text = fixed targets taken from the brief on the Coverage Summary sheet.

Sheet Test Cases
A1: Test ID | B1: Layer | C1: Feature | D1: FR Ref | E1: AC Ref(s) | F1: Priority | G1: Type | H1: Test Title | I1: Preconditions | J1: Test Steps | K1: Test Data | L1: Expected Result | M1: Tool / Location | N1: Automation Status | O1: Execution Status | P1: Executed By | Q1: Execution Date | R1: Defect ID | S1: Evidence Link | T1: JIRA Story
A2: T-UI-AUTH-001 | B2: Cypress (UI) | C2: User Authentication | D2: FR-001 | E2: FR-001-AC1 | F2: P0 | G2: Positive | H2: User login with valid email and password succeeds | I2: Active test customer account exists; app reachable; browser on login page | J2: 1. Open the login page 2. Enter a valid email and password 3. Click Login | K2: validUser in fixtures/users.json | L2: User is redirected to the dashboard; user name is displayed; session cookie/token is set | M2: cypress/e2e/auth.cy.js | N2: Planned | O2: Not Run
A3: T-UI-AUTH-002 | B3: Cypress (UI) | C3: User Authentication | D3: FR-001 | E3: FR-001-AC2 | F3: P0 | G3: Negative | H3: Login with invalid credentials is rejected with a clear error message | I3: Active test customer account exists; app reachable; browser on login page | J3: 1. Open the login page 2. Enter a valid email with a wrong password and click Login 3. Repeat with an unregistered email 4. Repeat with an empty password | K3: invalidUsers[] in fixtures/users.json | L3: Login is rejected each time; a clear, non-technical error is shown; user stays on the login page; no session is created; the message does not reveal which field was wrong | M3: cypress/e2e/auth.cy.ts | N3: Planned | O3: Not Run
A4: T-UI-AUTH-003 | B4: Cypress (UI) | C4: User Authentication | D4: FR-001 | E4: FR-001-AC3 | F4: P0 | G4: Positive | H4: Session persists across page navigation | I4: Active test customer account exists; app reachable; browser on login page | J4: 1. Log in 2. Navigate Dashboard > Orders > Tracking 3. Refresh the browser on each page | L4: User stays authenticated on every page and after refresh; no re-login prompt | M4: cypress/e2e/auth.cy.js | N4: Planned | O4: Not Run
A5: T-UI-AUTH-004 | B5: Cypress (UI) | C5: User Authentication | D5: FR-001 | E5: FR-001-AC4 | F5: P0 | G5: Boundary | H5: Session expires after 30 minutes of inactivity | I5: Active test customer account exists; app reachable; browser on login page | J5: 1. Log in 2. Advance the clock 29 minutes (cy.clock/cy.tick) and perform an action 3. Advance a further 2 minutes with no activity and perform an action | K5: If the server enforces expiry, use a short-lived token via test config instead of cy.clock | L5: At 29 minutes the session is still valid; after 30+ minutes the user is redirected to login with a session-expired message and protected pages are inaccessible | M5: cypress/e2e/auth.cy.ts | N5: Planned | O5: Not Run
A6: T-UI-ORD-001 | B6: Cypress (UI) | C6: Order Management | D6: FR-002 | E6: FR-002-AC1 | F6: P0 | G6: Positive | H6: Add a product to the order with a valid quantity | I6: Logged-in customer; catalogue seeded with in-stock SKUs at known prices; tax rate known | J6: 1. Search for an in-stock product 2. Set quantity to 2 3. Click Add to cart 4. Open the cart | K6: SKU-001 qty 2 | L6: Cart shows the product with quantity 2, unit price and the correct line subtotal | M6: cypress/e2e/orders.cy.ts | N6: Planned | O6: Not Run
A7: T-UI-ORD-002 | B7: Cypress (UI) | C7: Order Management | D7: FR-002 | E7: FR-002-AC1 | F7: P0 | G7: Negative / Boundary | H7: Quantity validation rejects zero, negative, non-numeric and above-stock quantities | I7: Logged-in customer; catalogue seeded with in-stock SKUs at known prices; tax rate known | J7: 1. Enter quantity 0 2. Enter -1 3. Enter 'abc' 4. Enter stock + 1 5. Enter exactly the available stock | K7: Product with known stock level | L7: 0, -1, 'abc' and stock + 1 are rejected with a validation message and the cart is unchanged; quantity equal to available stock is accepted | M7: cypress/e2e/orders.cy.ts | N7: Planned | O7: Not Run
A8: T-UI-ORD-003 | B8: Cypress (UI) | C8: Order Management | D8: FR-002 | E8: FR-002-AC2 | F8: P0 | G8: Positive | H8: Order total equals items x price + tax | I8: Logged-in customer; catalogue seeded with in-stock SKUs at known prices; tax rate known | J8: 1. Add two different products with different quantities 2. Read the displayed subtotal, tax and total | K8: SKU-001 x2, SKU-002 x3 | L8: Total = SUM(qty x unit price) + tax, rounded to 2 decimals, and matches the value calculated independently from fixtures | M8: cypress/e2e/orders.cy.ts | N8: Planned | O8: Not Run
A9: T-UI-ORD-004 | B9: Cypress (UI) | C9: Order Management | D9: FR-002 | E9: FR-002-AC3 | F9: P0 | G9: Positive | H9: Valid coupon code applies the correct discount | I9: Logged-in customer; catalogue seeded with in-stock SKUs at known prices; tax rate known | J9: 1. Add products to the cart 2. Enter a valid coupon code 3. Click Apply | K9: coupons.valid in fixtures | L9: Discount line is displayed; total is reduced by the correct amount/percentage; tax is recalculated per business rule | M9: cypress/e2e/orders.cy.ts | N9: Planned | O9: Not Run
A10: T-UI-ORD-005 | B10: Cypress (UI) | C10: Order Management | D10: FR-002 | E10: FR-002-AC3 | F10: P0 | G10: Negative | H10: Invalid, expired or already-used coupon is rejected | I10: Logged-in customer; catalogue seeded with in-stock SKUs at known prices; tax rate known | J10: 1. Add products to the cart 2. Apply an invalid code 3. Apply an expired code 4. Apply a single-use code that was already redeemed | K10: coupons.invalid / expired / used | L10: Each coupon is rejected with a clear message; order total is unchanged | M10: cypress/e2e/orders.cy.ts | N10: Planned | O10: Not Run
A11: T-UI-ORD-006 | B11: Cypress (UI) | C11: Order Management | D11: FR-002 | E11: FR-002-AC4 | F11: P0 | G11: Positive | H11: Order quantity can be modified before payment and totals recalculate | I11: Logged-in customer; catalogue seeded with in-stock SKUs at known prices; tax rate known | J11: 1. Create an unpaid order 2. Change a line quantity from 2 to 4 3. Save | L11: Line subtotal, tax and order total are recalculated correctly and persisted after refresh | M11: cypress/e2e/orders.cy.ts | N11: Planned | O11: Not Run
A12: T-UI-ORD-007 | B12: Cypress (UI) | C12: Order Management | D12: FR-002 | E12: FR-002-AC4 | F12: P0 | G12: Positive | H12: Delivery address can be changed before payment | I12: Logged-in customer; catalogue seeded with in-stock SKUs at known prices; tax rate known | J12: 1. Create an unpaid order 2. Edit the delivery address to another saved address 3. Save | L12: New address is shown on the order summary and persists after refresh | M12: cypress/e2e/orders.cy.ts | N12: Planned | O12: Not Run
A13: T-UI-ORD-008 | B13: Cypress (UI) | C13: Order Management | D13: FR-002 | E13: FR-002-AC5 | F13: P0 | G13: Negative | H13: Order cannot be modified after payment | I13: Logged-in customer; catalogue seeded with in-stock SKUs at known prices; tax rate known | J13: 1. Open a paid order 2. Look for edit quantity/address controls 3. Attempt to open the edit URL directly | L13: Edit controls are hidden or disabled; direct URL access is blocked with a message; order data is unchanged | M13: cypress/e2e/orders.cy.ts | N13: Planned | O13: Not Run
A14: T-UI-ORD-009 | B14: Cypress (UI) | C14: Order Management | D14: FR-002 | E14: FR-002-AC6 | F14: P0 | G14: Positive | H14: Cancelling an order updates its status and returns inventory | I14: Logged-in customer; catalogue seeded with in-stock SKUs at known prices; tax rate known | J14: 1. Note the product's available stock 2. Create and cancel an order for quantity 2 3. Re-open the product page | L14: Order status shows Cancelled; displayed available stock is restored to the original level | M14: cypress/e2e/orders.cy.ts | N14: Planned | O14: Not Run
A15: T-UI-ORD-010 | B15: Cypress (UI) | C15: Order Management | D15: FR-002 | E15: FR-002-AC7 | F15: P0 | G15: Negative | H15: Rapid double submission creates only one order | I15: Logged-in customer; catalogue seeded with in-stock SKUs at known prices; tax rate known | J15: 1. Prepare a valid cart 2. Double-click Place Order (or submit twice within 1 second) 3. Open order history | L15: Only one order is created; the second submission is ignored or returns the same order | M15: cypress/e2e/orders.cy.ts | N15: Planned | O15: Not Run
A16: T-UI-PAY-001 | B16: Cypress (UI) | C16: Payment Processing | D16: FR-003 | E16: FR-003-AC2 | F16: P0 | G16: Positive | H16: Payment with a valid card succeeds | I16: Logged-in customer with an order awaiting payment; payment sandbox test cards available | J16: 1. Open payment for an unpaid order 2. Enter a valid sandbox card, expiry and CVV 3. Click Pay | K16: cards.valid in fixtures | L16: Payment is confirmed; order status changes to Paid; confirmation/receipt is displayed | M16: cypress/e2e/payments.cy.ts | N16: Planned | O16: Not Run
A17: T-UI-PAY-002 | B17: Cypress (UI) | C17: Payment Processing | D17: FR-003 | E17: FR-003-AC1 | F17: P0 | G17: Negative | H17: Invalid card number format is rejected | I17: Logged-in customer with an order awaiting payment; payment sandbox test cards available | J17: 1. Enter a card number with letters 2. Enter a too-short number 3. Enter a 16-digit number that fails the Luhn check | K17: cards.badNumber[] | L17: Each entry is rejected with an inline validation message; Pay does not submit; no charge is attempted | M17: cypress/e2e/payments.cy.ts | N17: Planned | O17: Not Run
A18: T-UI-PAY-003 | B18: Cypress (UI) | C18: Payment Processing | D18: FR-003 | E18: FR-003-AC1 | F18: P0 | G18: Boundary | H18: Expired card is rejected | I18: Logged-in customer with an order awaiting payment; payment sandbox test cards available | J18: 1. Enter a valid number with an expiry in the previous month 2. Enter the current month and year | K18: cards.expired | L18: Previous month is rejected with an expiry message; current month is accepted | M18: cypress/e2e/payments.cy.ts | N18: Planned | O18: Not Run
A19: T-UI-PAY-004 | B19: Cypress (UI) | C19: Payment Processing | D19: FR-003 | E19: FR-003-AC1 | F19: P0 | G19: Negative | H19: Invalid CVV is rejected | I19: Logged-in customer with an order awaiting payment; payment sandbox test cards available | J19: 1. Enter a valid card with a 2-digit CVV 2. Enter non-numeric CVV 3. Leave CVV empty | L19: Each CVV is rejected with a clear validation message; payment is not submitted | M19: cypress/e2e/payments.cy.ts | N19: Planned | O19: Not Run
A20: T-UI-PAY-005 | B20: Cypress (UI) | C20: Payment Processing | D20: FR-003 | E20: FR-003-AC3 | F20: P0 | G20: Negative | H20: Declined card is handled gracefully | I20: Logged-in customer with an order awaiting payment; payment sandbox test cards available | J20: 1. Pay with the sandbox 'decline' test card 2. Observe the result 3. Open the order | K20: cards.declined | L20: A friendly decline message is shown (no technical error/stack trace); order remains unpaid; user can retry | M20: cypress/e2e/payments.cy.ts | N20: Planned | O20: Not Run
A21: T-UI-PAY-006 | B21: Cypress (UI) | C21: Payment Processing | D21: FR-003 | E21: FR-003-AC4 | F21: P0 | G21: Negative | H21: Double-clicking Pay does not charge twice | I21: Logged-in customer with an order awaiting payment; payment sandbox test cards available | J21: 1. Enter valid card details 2. Double-click Pay 3. Check order and payment status | L21: Only one payment is processed; Pay button is disabled after the first click; order shows a single payment | M21: cypress/e2e/payments.cy.ts | N21: Planned | O21: Not Run
A22: T-UI-DEL-001 | B22: Cypress (UI) | C22: Delivery Tracking | D22: FR-004 | E22: FR-004-AC2 | F22: P0 | G22: Positive | H22: Tracking number is assigned and visible on the order details page | I22: Paid orders exist in Shipped and Delivered states; one paid order not yet shipped; one unpaid order | J22: 1. Open a shipped order 2. View the delivery section | L22: A tracking number is displayed and matches the format and value in the API response | M22: cypress/e2e/delivery.cy.ts | N22: Planned | O22: Not Run
A23: T-UI-DEL-002 | B23: Cypress (UI) | C23: Delivery Tracking | D23: FR-004 | E23: FR-004-AC3 | F23: P0 | G23: Positive | H23: Shipped status is displayed correctly | I23: Paid orders exist in Shipped and Delivered states; one paid order not yet shipped; one unpaid order | J23: 1. Open an order whose shipment is Shipped 2. Check the status and tracking timeline | L23: Status shows Shipped with a timestamp; timeline lists earlier steps in order | M23: cypress/e2e/delivery.cy.ts | N23: Planned | O23: Not Run
A24: T-UI-DEL-003 | B24: Cypress (UI) | C24: Delivery Tracking | D24: FR-004 | E24: FR-004-AC3 | F24: P0 | G24: Positive | H24: Delivered status is displayed after the shipment is delivered | I24: Paid orders exist in Shipped and Delivered states; one paid order not yet shipped; one unpaid order | J24: 1. Open an order whose shipment is Delivered 2. Check the status and timeline | L24: Status shows Delivered with a timestamp; timeline shows Shipped before Delivered | M24: cypress/e2e/delivery.cy.ts | N24: Planned | O24: Not Run
A25: T-UI-DEL-004 | B25: Cypress (UI) | C25: Delivery Tracking | D25: FR-004 | E25: FR-004-AC1 | F25: P0 | G25: Negative | H25: Unpaid order shows no shipment or tracking number | I25: Paid orders exist in Shipped and Delivered states; one paid order not yet shipped; one unpaid order | J25: 1. Open an unpaid order 2. View the delivery section | L25: No shipment is created or shown and no tracking number is displayed; status reflects awaiting payment | M25: cypress/e2e/delivery.cy.ts | N25: Planned | O25: Not Run
A26: T-UI-DEL-005 | B26: Cypress (UI) | C26: Delivery Tracking | D26: FR-004 | E26: FR-004-AC2 | F26: P0 | G26: Positive / Negative | H26: Tracking page finds a shipment by tracking number and handles unknown numbers | I26: Paid orders exist in Shipped and Delivered states; one paid order not yet shipped; one unpaid order | J26: 1. Open the tracking page 2. Enter a valid tracking number 3. Enter an unknown tracking number | L26: Valid number shows shipment status and history; unknown number shows a clear 'not found' message | M26: cypress/e2e/delivery.cy.ts | N26: Planned | O26: Not Run
A27: T-UI-DEL-006 | B27: Cypress (UI) | C27: Delivery Tracking | D27: FR-004 | E27: FR-004-AC5 | F27: P0 | G27: Positive | H27: Proof of delivery is visible on a delivered order | I27: Paid orders exist in Shipped and Delivered states; one paid order not yet shipped; one unpaid order | J27: 1. Open a delivered order 2. View the proof of delivery section | L27: POD details (received-by/signature or photo reference and timestamp) are displayed | M27: cypress/e2e/delivery.cy.ts | N27: Planned | O27: Not Run
A28: T-UI-DASH-001 | B28: Cypress (UI) | C28: User Dashboard | D28: FR-006 | E28: FR-006-AC1 | F28: P1 | G28: Positive | H28: Order history is displayed with pagination | I28: Logged-in customer with 25+ historical orders of mixed status, date and price | J28: 1. Open the dashboard order history 2. Note the page size and total 3. Go to next, previous and last pages | L28: Page size is respected; no order is duplicated or missing across pages; page controls are enabled/disabled correctly at the first and last page | M28: cypress/e2e/dashboard.cy.ts | N28: Planned | O28: Not Run
A29: T-UI-DASH-002 | B29: Cypress (UI) | C29: User Dashboard | D29: FR-006 | E29: FR-006-AC2 | F29: P1 | G29: Positive | H29: Order history can be filtered by date range, status and price | I29: Logged-in customer with 25+ historical orders of mixed status, date and price | J29: 1. Filter by a date range 2. Filter by status 3. Filter by price range 4. Combine filters 5. Clear filters | L29: Only matching orders are shown for each filter and for combinations; counts are correct; clearing restores the full list | M29: cypress/e2e/dashboard.cy.ts | N29: Planned | O29: Not Run
A30: T-UI-DASH-003 | B30: Cypress (UI) | C30: User Dashboard | D30: FR-006 | E30: FR-006-AC3 | F30: P1 | G30: Positive | H30: Saved addresses can be added, edited and deleted | I30: Logged-in customer with 25+ historical orders of mixed status, date and price | J30: 1. Add a new address 2. Edit it 3. Delete it 4. Try saving an address with a missing mandatory field | L30: Add/edit/delete reflect immediately and persist after refresh; missing mandatory field is rejected with a message | M30: cypress/e2e/dashboard.cy.ts | N30: Planned | O30: Not Run
A31: T-UI-DASH-004 | B31: Cypress (UI) | C31: User Dashboard | D31: FR-006 | E31: FR-006-AC4 | F31: P1 | G31: Positive / Negative | H31: Profile name, email and phone can be updated and are validated | I31: Logged-in customer with 25+ historical orders of mixed status, date and price | J31: 1. Update name, email and phone with valid values and save 2. Enter an invalid email 3. Enter an invalid phone number | L31: Valid changes persist after refresh; invalid email and phone are rejected with clear messages | M31: cypress/e2e/dashboard.cy.ts | N31: Planned | O31: Not Run
A32: T-UI-RET-001 | B32: Cypress (UI) | C32: Returns & Refunds | D32: FR-005 | E32: FR-005-AC1 | F32: P1 | G32: Positive | H32: Return can be initiated within the 30-day window | I32: Customer has a delivered order inside the 30-day window and one outside it | J32: 1. Open a delivered order inside 30 days 2. Click Return 3. Select item(s) and reason 4. Submit | L32: Return request is created with status Requested and a return reference is displayed | M32: cypress/e2e/returns.cy.ts | N32: Planned | O32: Not Run
... A41: T-UI-XBR-006 | B41: Cypress (UI) | C41: Cross-Browser Support | D41: FR-004 | E41: FR-004-AC2; FR-004-AC3 | F41: P2 | G41: Positive | H41: Tracking page renders correctly at 1920x1080 and 1366x768 | I41: Same seeded data as the main suite; run with --browser chrome / firefox / edge | J41: 1. Set the viewport to 1920x1080 and open a shipped order 2. Repeat at 1366x768 | L41: Tracking number and status timeline are visible, readable and not truncated at both resolutions | M41: cypress/e2e/cross-browser.cy.ts | N41: Planned | O41: Not Run
A42: T-API-AUTH-001 | B42: Postman (API) | C42: Authentication APIs | D42: FR-001 | E42: FR-001-AC1; FR-001-AC3 | F42: P0 | G42: Positive | H42: POST /auth/login with valid credentials returns 200 and a usable JWT | I42: Postman environment holds base_url; test users seeded (one active, one disposable for lockout) | J42: 1. POST valid credentials 2. Assert status, schema (token, expiry, user id), response time 3. Decode the JWT and check claims 4. Call a protected endpoint with the token twice | K42: validUser | L42: 200 OK; token present with correct claims and expiry; the token is accepted on repeated authenticated calls | M42: postman/collections/Auth | N42: Planned | O42: Not Run
A43: T-API-AUTH-002 | B43: Postman (API) | C43: Authentication APIs | D43: FR-001 | E43: FR-001-AC2; FR-001-AC7 | F43: P0 | G43: Negative / Boundary | H43: Account locks after 5 consecutive failed logins | I43: Postman environment holds base_url; test users seeded (one active, one disposable for lockout) | J43: 1. POST 4 wrong passwords for a disposable user (expect 401 with a generic error) 2. POST the 5th wrong password 3. POST the correct password | K43: lockoutUser (disposable) | L43: Failures 1-5 return 401 with a generic error; the correct password after the 5th failure is refused with a locked status (e.g. 423/403) and a lockout message; a different user is unaffected | M43: postman/collections/Auth | N43: Planned | O43: Not Run
A44: T-API-AUTH-003 | B44: Postman (API) | C44: Authentication APIs | D44: FR-001 | E44: FR-001-AC5 | F44: P0 | G44: Positive | H44: Logout invalidates the session token | I44: Postman environment holds base_url; test users seeded (one active, one disposable for lockout) | J44: 1. Log in and capture the token 2. Call a protected endpoint (200) 3. Call POST /auth/logout 4. Re-use the same token | L44: Logout returns 200/204; the same token is then rejected with 401 | M44: postman/collections/Auth | N44: Planned | O44: Not Run
A45: T-API-AUTH-004 | B45: Postman (API) | C45: Authentication APIs | D45: FR-001 | E45: FR-001-AC6 | F45: P0 | G45: Positive / Negative | H45: Password reset link issues a single-use token and updates the password | I45: Postman environment holds base_url; test users seeded (one active, one disposable for lockout) | J45: 1. POST forgot-password for a known email 2. Retrieve the reset token from the test mailbox 3. POST reset-password with a new password 4. Log in with the new password 5. Re-use the reset token | K45: Test mailbox or mail-trap access | L45: A reset email/token is issued; the password is changed; the new password works and the old one fails; re-using the token is rejected; unknown emails get a generic response | M45: postman/collections/Auth | N45: Planned | O45: Not Run
A46: T-API-ORD-001 | B46: Postman (API) | C46: Order APIs | D46: FR-002 | E46: FR-002-AC1 | F46: P0 | G46: Positive | H46: POST /orders creates an order with valid items | I46: Valid auth token in environment; SKUs, coupons and addresses seeded | J46: 1. POST an order with valid SKUs and quantities 2. Assert status, schema and values | L46: 201 Created; order id returned; line items, quantities and unit prices match the request/catalogue | M46: postman/collections/Orders | N46: Planned | O46: Not Run
A47: T-API-ORD-002 | B47: Postman (API) | C47: Order APIs | D47: FR-002 | E47: FR-002-AC1 | F47: P0 | G47: Negative / Boundary | H47: POST /orders rejects invalid quantities | I47: Valid auth token in environment; SKUs, coupons and addresses seeded | J47: 1. POST quantity 0 2. POST quantity -1 3. POST a string quantity 4. POST quantity above available stock 5. POST quantity equal to stock | L47: Invalid quantities return 400/422 with field-level messages and no order is created; quantity equal to stock is accepted | M47: postman/collections/Orders | N47: Planned | O47: Not Run
A48: T-API-ORD-003 | B48: Postman (API) | C48: Order APIs | D48: FR-002 | E48: FR-002-AC2 | F48: P0 | G48: Positive | H48: Order total equals items x price + tax | I48: Valid auth token in environment; SKUs, coupons and addresses seeded | J48: 1. Create an order with multiple items 2. Compute the expected total in a Postman test script 3. Compare with the response | L48: subtotal, tax and total in the response equal the expected values to 2 decimals | M48: postman/collections/Orders | N48: Planned | O48: Not Run
A49: T-API-ORD-004 | B49: Postman (API) | C49: Order APIs | D49: FR-002 | E49: FR-002-AC3 | F49: P0 | G49: Positive | H49: Valid coupon applies the correct discount | I49: Valid auth token in environment; SKUs, coupons and addresses seeded | J49: 1. POST/PUT apply-coupon with a valid code 2. Assert the response | K49: coupons.valid | L49: 200 OK; discount amount is correct; total reduced accordingly | M49: postman/collections/Orders | N49: Planned | O49: Not Run
A50: T-API-ORD-005 | B50: Postman (API) | C50: Order APIs | D50: FR-002 | E50: FR-002-AC3 | F50: P0 | G50: Negative | H50: Invalid, expired and reused coupons are rejected | I50: Valid auth token in environment; SKUs, coupons and addresses seeded | J50: 1. Apply an invalid code 2. Apply an expired code 3. Apply an already-used single-use code | K50: coupons.invalid / expired / used | L50: Each returns 400/422 (or 404) with a clear error code; order total is unchanged | M50: postman/collections/Orders | N50: Planned | O50: Not Run
A51: T-API-ORD-006 | B51: Postman (API) | C51: Order APIs | D51: FR-002 | E51: FR-002-AC4 | F51: P0 | G51: Positive | H51: PUT /orders/{id} modifies quantity and address before payment | I51: Valid auth token in environment; SKUs, coupons and addresses seeded | J51: 1. Create an unpaid order 2. PUT a new quantity 3. PUT a new address 4. GET the order | L51: 200 OK; the GET shows the new quantity, recalculated totals and the new address | M51: postman/collections/Orders | N51: Planned | O51: Not Run
A52: T-API-ORD-007 | B52: Postman (API) | C52: Order APIs | D52: FR-002 | E52: FR-002-AC5 | F52: P0 | G52: Negative | H52: Modifying an order after payment is rejected | I52: Valid auth token in environment; SKUs, coupons and addresses seeded | J52: 1. Take a paid order 2. PUT a quantity change 3. PUT an address change 4. GET the order | L52: Both calls return 409/403/422 with a clear reason; the order is unchanged | M52: postman/collections/Orders | N52: Planned | O52: Not Run
A53: T-API-ORD-008 | B53: Postman (API) | C53: Order APIs | D53: FR-002 | E53: FR-002-AC6 | F53: P0 | G53: Positive | H53: Cancelling an order sets status to Cancelled and releases stock | I53: Valid auth token in environment; SKUs, coupons and addresses seeded | J53: 1. GET stock for the SKU 2. Create an order and cancel it 3. GET the order and GET the stock | L53: Order status is Cancelled; stock returns to the original level | M53: postman/collections/Orders | N53: Planned | O53: Not Run
A54: T-API-ORD-009 | B54: Postman (API) | C54: Order APIs | D54: FR-002 | E54: FR-002-AC7 | F54: P0 | G54: Negative | H54: Duplicate order submission with the same idempotency key creates one order | I54: Valid auth token in environment; SKUs, coupons and addresses seeded | J54: 1. POST an order with an Idempotency-Key 2. POST the identical request again with the same key 3. GET the customer's orders | L54: The second call returns the original order (or 409) and no second order exists | M54: postman/collections/Orders | N54: Planned | O54: Not Run
A55: T-API-ORD-010 | B55: Postman (API) | C55: Order APIs | D55: FR-006 | E55: FR-006-AC1; FR-006-AC2 | F55: P0 | G55: Positive | H55: GET /orders returns paginated and filtered order history | I55: Valid auth token in environment; SKUs, coupons and addresses seeded | J55: 1. GET page 1 with page size 10 2. GET page 2 3. Filter by status 4. Filter by date range 5. Filter by price range | L55: Page size, total count and links are correct with no duplicates across pages; each filter returns only matching orders | M55: postman/collections/Orders | N55: Planned | O55: Not Run
A56: T-API-PAY-001 | B56: Postman (API) | C56: Payment APIs | D56: FR-003 | E56: FR-003-AC2 | F56: P0 | G56: Positive | H56: Payment with a valid card is authorized | I56: Valid auth token; unpaid order exists; sandbox test card numbers available | J56: 1. POST payment for an unpaid order with a valid sandbox card 2. GET the payment 3. GET the order | K56: cards.valid | L56: 200/201 with status Authorized/Settled; payment amount equals the order total; order status becomes Paid | M56: postman/collections/Payments | N56: Planned | O56: Not Run
A57: T-API-PAY-002 | B57: Postman (API) | C57: Payment APIs | D57: FR-003 | E57: FR-003-AC1 | F57: P0 | G57: Negative | H57: Invalid card number is rejected | I57: Valid auth token; unpaid order exists; sandbox test card numbers available | J57: 1. POST a non-numeric number 2. POST a short number 3. POST a number that fails Luhn | L57: 400/422 with a card-number validation error; no payment record created | M57: postman/collections/Payments | N57: Planned | O57: Not Run
A58: T-API-PAY-003 | B58: Postman (API) | C58: Payment APIs | D58: FR-003 | E58: FR-003-AC1 | F58: P0 | G58: Boundary | H58: Expired card is rejected | I58: Valid auth token; unpaid order exists; sandbox test card numbers available | J58: 1. POST expiry = previous month 2. POST expiry = current month | L58: Previous month rejected with an expiry error; current month accepted | M58: postman/collections/Payments | N58: Planned | O58: Not Run
A59: T-API-PAY-004 | B59: Postman (API) | C59: Payment APIs | D59: FR-003 | E59: FR-003-AC1 | F59: P0 | G59: Negative | H59: Invalid CVV is rejected | I59: Valid auth token; unpaid order exists; sandbox test card numbers available | J59: 1. POST a 2-digit CVV 2. POST a non-numeric CVV 3. POST with CVV missing | L59: 400/422 with a CVV validation error each time; no charge made | M59: postman/collections/Payments | N59: Planned | O59: Not Run
A60: T-API-PAY-005 | B60: Postman (API) | C60: Payment APIs | D60: FR-003 | E60: FR-003-AC3 | F60: P0 | G60: Negative | H60: Declined card returns a graceful, structured decline response | I60: Valid auth token; unpaid order exists; sandbox test card numbers available | J60: 1. POST payment with the sandbox decline card 2. GET the order | K60: cards.declined | L60: Structured decline (e.g. 402) with a decline code and message and no stack trace; order remains unpaid | M60: postman/collections/Payments | N60: Planned | O60: Not Run
A61: T-API-PAY-006 | B61: Postman (API) | C61: Payment APIs | D61: FR-003 | E61: FR-003-AC4 | F61: P0 | G61: Negative | H61: Duplicate payment for the same order does not double-charge | I61: Valid auth token; unpaid order exists; sandbox test card numbers available | J61: 1. POST payment with an Idempotency-Key 2. POST the same payment again 3. POST a new payment for the already paid order 4. GET payments for the order | L61: Only one successful payment exists; repeated calls return the original result or 409 | M61: postman/collections/Payments | N61: Planned | O61: Not Run
A62: T-API-PAY-007 | B62: Postman (API) | C62: Payment APIs | D62: FR-003 | E62: FR-003-AC5 | F62: P0 | G62: Positive | H62: Full refund returns the full amount to the original payment method | I62: Valid auth token; unpaid order exists; sandbox test card numbers available | J62: 1. POST refund for a paid order 2. GET the refund 3. GET the payment | L62: Refund amount equals the amount paid; refund references the original payment; status is Refunded/Completed | M62: postman/collections/Payments | N62: Planned | O62: Not Run
A63: T-API-PAY-008 | B63: Postman (API) | C63: Payment APIs | D63: FR-003 | E63: FR-003-AC5 | F63: P0 | G63: Positive / Boundary | H63: Partial refund works and refunds above the paid amount are rejected | I63: Valid auth token; unpaid order exists; sandbox test card numbers available | J63: 1. POST a partial refund 2. POST a second refund that would exceed the paid amount 3. GET refunds | L63: The partial refund succeeds; the over-refund is rejected with 400/409; total refunded never exceeds the amount paid | M63: postman/collections/Payments | N63: Planned | O63: Not Run
A64: T-API-SHP-001 | B64: Postman (API) | C64: Shipment APIs | D64: FR-004 | E64: FR-004-AC1 | F64: P0 | G64: Positive | H64: Shipment is created after payment is confirmed | I64: Valid auth token (customer + admin/warehouse role); paid and unpaid orders exist | J64: 1. Pay for an order 2. GET shipments for the order | L64: A shipment exists with status Processing/Created and is linked to the paid order | M64: postman/collections/Shipments | N64: Planned | O64: Not Run
A65: T-API-SHP-002 | B65: Postman (API) | C65: Shipment APIs | D65: FR-004 | E65: FR-004-AC1 | F65: P0 | G65: Negative | H65: No shipment is created for an unpaid order | I65: Valid auth token (customer + admin/warehouse role); paid and unpaid orders exist | J65: 1. Create an unpaid order 2. Attempt POST /shipments for it 3. GET shipments for the order | L65: Creation is rejected (400/409) and no shipment exists | M65: postman/collections/Shipments | N65: Planned | O65: Not Run
A66: T-API-SHP-003 | B66: Postman (API) | C66: Shipment APIs | D66: FR-004 | E66: FR-004-AC2 | F66: P0 | G66: Positive | H66: Tracking number is assigned, unique and correctly formatted | I66: Valid auth token (customer + admin/warehouse role); paid and unpaid orders exist | J66: 1. Create shipments for two orders 2. Assert tracking numbers | L66: Each shipment has a non-empty tracking number matching the agreed format; the two numbers differ | M66: postman/collections/Shipments | N66: Planned | O66: Not Run
A67: T-API-SHP-004 | B67: Postman (API) | C67: Shipment APIs | D67: FR-004 | E67: FR-004-AC3 | F67: P0 | G67: Positive | H67: Shipment status progresses Processing to Shipped | I67: Valid auth token (customer + admin/warehouse role); paid and unpaid orders exist | J67: 1. PATCH the status to Shipped (warehouse role) 2. GET the shipment | L67: 200 OK; status is Shipped with a timestamp; history lists both states in order | M67: postman/collections/Shipments | N67: Planned | O67: Not Run
A68: T-API-SHP-005 | B68: Postman (API) | C68: Shipment APIs | D68: FR-004 | E68: FR-004-AC3 | F68: P0 | G68: Negative | H68: Invalid shipment status transitions are rejected | I68: Valid auth token (customer + admin/warehouse role); paid and unpaid orders exist | J68: 1. Try Delivered > Shipped 2. Try skipping from Processing to Delivered (if disallowed) 3. Use a customer token to update status | L68: Invalid transitions return 400/409 and customers get 403; status is unchanged | M68: postman/collections/Shipments | N68: Planned | O68: Not Run
A69: T-API-SHP-006 | B69: Postman (API) | C69: Shipment APIs | D69: FR-004 | E69: FR-004-AC4 | F69: P0 | G69: Positive | H69: Shipped notification (SMS/Email) is triggered | I69: Valid auth token (customer + admin/warehouse role); paid and unpaid orders exist | J69: 1. Move a shipment to Shipped 2. Check the notification endpoint, test mailbox or SMS stub | L69: One email and/or SMS is sent to the customer, containing the order reference and tracking number | M69: postman/collections/Shipments | N69: Planned | O69: Not Run
A70: T-API-DEL-001 | B70: Postman (API) | C70: Delivery APIs | D70: FR-004 | E70: FR-004-AC2; FR-004-AC3 | F70: P0 | G70: Positive | H70: GET tracking by tracking number returns status and history | I70: Valid auth token; shipment with a tracking number exists | J70: 1. GET /tracking/{trackingNumber} 2. Assert fields 3. GET with an unknown number | L70: Valid number returns 200 with the current status and ordered history; unknown number returns 404 with a clear message | M70: postman/collections/Delivery | N70: Planned | O70: Not Run
A71: T-API-DEL-002 | B71: Postman (API) | C71: Delivery APIs | D71: FR-004 | E71: FR-004-AC3 | F71: P0 | G71: Positive | H71: Marking a shipment Delivered updates the status | I71: Valid auth token; shipment with a tracking number exists | J71: 1. PATCH the shipment to Delivered 2. GET the shipment and the order | L71: Shipment and order show Delivered with a delivery timestamp | M71: postman/collections/Delivery | N71: Planned | O71: Not Run
A72: T-API-DEL-003 | B72: Postman (API) | C72: Delivery APIs | D72: FR-004 | E72: FR-004-AC5 | F72: P0 | G72: Positive | H72: Proof of delivery is recorded | I72: Valid auth token; shipment with a tracking number exists | J72: 1. Submit delivery with POD data (recipient name, signature/photo reference, timestamp) 2. GET the shipment | L72: POD is stored and returned; delivery without mandatory POD fields is rejected | M72: postman/collections/Delivery | N72: Planned | O72: Not Run
A73: T-API-DEL-004 | B73: Postman (API) | C73: Delivery APIs | D73: FR-004 | E73: FR-004-AC4 | F73: P0 | G73: Positive | H73: Delivered notification (SMS/Email) is triggered | I73: Valid auth token; shipment with a tracking number exists | J73: 1. Mark Delivered 2. Check the notification endpoint, test mailbox or SMS stub | L73: A delivered notification is sent once to the customer | M73: postman/collections/Delivery | N73: Planned | O73: Not Run
A74: T-API-RET-001 | B74: Postman (API) | C74: Returns APIs | D74: FR-005 | E74: FR-005-AC1 | F74: P1 | G74: Positive / Boundary | H74: POST /returns inside the window is accepted; boundary day 30 accepted and day 31 rejected | I74: Valid auth token; delivered orders aged inside and outside 30 days | J74: 1. Return an order delivered 10 days ago 2. Return an order delivered exactly 30 days ago 3. Return an order delivered 31 days ago | K74: Orders with delivery dates set via the seed script | L74: 10 days and 30 days: 201 Created; 31 days: 400/422 with a return-window error and no return created | M74: postman/collections/Returns | N74: Planned | O74: Not Run
A75: T-API-RET-002 | B75: Postman (API) | C75: Returns APIs | D75: FR-005 | E75: FR-005-AC2 | F75: P1 | G75: Positive | H75: Refund amount is calculated correctly for a return | I75: Valid auth token; delivered orders aged inside and outside 30 days | J75: 1. Return one item from an order that used a coupon 2. GET the return/refund details | L75: Refund = item price less proportional discount plus applicable tax, matching the independently calculated value | M75: postman/collections/Returns | N75: Planned | O75: Not Run
A76: T-API-RET-003 | B76: Postman (API) | C76: Returns APIs | D76: FR-005 | E76: FR-005-AC3 | F76: P1 | G76: Positive | H76: Refund is issued to the original payment method | I76: Valid auth token; delivered orders aged inside and outside 30 days | J76: 1. Complete the return 2. GET the refund 3. GET the original payment | L76: The refund references the original payment id and method; no refund to a different method is possible | M76: postman/collections/Returns | N76: Planned | O76: Not Run
A77: T-API-RET-004 | B77: Postman (API) | C77: Returns APIs | D77: FR-005 | E77: FR-005-AC1; FR-005-AC2 | F77: P1 | G77: Negative | H77: Return of an item that was not part of the order is rejected | I77: Valid auth token; delivered orders aged inside and outside 30 days | J77: 1. POST a return containing an SKU not on the order 2. POST a quantity above the quantity ordered | L77: 400/422 with a clear error; no return or refund is created | M77: postman/collections/Returns | N77: Planned | O77: Not Run
A78: T-API-ERR-001 | B78: Postman (API) | C78: Global Error Handling | D78: FR-001 | E78: FR-001-AC2 | F78: P0 | G78: Negative | H78: Unauthenticated and invalid-token requests return 401 with a consistent error schema | I78: Postman environment configured; valid and invalid tokens available | J78: 1. Call protected endpoints with no token 2. Call with a tampered token 3. Call with an expired token | L78: 401 each time; the JSON error body has the standard fields (code, message); no internal details leaked | M78: postman/collections/ErrorHandling | N78: Planned | O78: Not Run
A79: T-API-ERR-002 | B79: Postman (API) | C79: Global Error Handling | D79: FR-002 | E79: FR-002-AC1 | F79: P0 | G79: Negative | H79: Malformed or incomplete requests return 400 with field-level errors | I79: Postman environment configured; valid and invalid tokens available | J79: 1. POST invalid JSON 2. POST with required fields missing 3. POST with wrong data types | L79: 400 with a clear validation error naming the offending fields; no server error | M79: postman/collections/ErrorHandling | N79: Planned | O79: Not Run
A80: T-API-ERR-003 | B80: Postman (API) | C80: Global Error Handling | D80: FR-002 | E80: FR-002-AC7 | F80: P0 | G80: Negative | H80: Requests for non-existent resources return 404 without leaking internals | I80: Postman environment configured; valid and invalid tokens available | J80: 1. GET an unknown order id 2. GET another customer's order id 3. GET an unknown route | L80: 404 (or 403 for another user's order) with the standard error body; no stack trace or SQL in the response | M80: postman/collections/ErrorHandling | N80: Planned | O80: Not Run
A81: T-API-ERR-004 | B81: Postman (API) | C81: Global Error Handling | D81: FR-006 | E81: FR-006-AC3; FR-006-AC4 | F81: P0 | G81: Positive / Negative | H81: Profile and saved-address endpoints validate input and persist valid changes | I81: Postman environment configured; valid and invalid tokens available | J81: 1. PUT a valid profile update and GET the profile 2. PUT an invalid email and an invalid phone 3. POST a valid address and GET the list 4. POST an address with a missing mandatory field | L81: Valid changes return 200/201 and are visible on GET; invalid input returns 400 with field errors and nothing is saved | M81: postman/collections/ErrorHandling | N81: Planned | O81: Not Run
A82: T-DB-ORD-001 | B82: SQL (DB) | C82: Order Data Integrity | D82: FR-007 | E82: FR-007-AC2; FR-007-AC3 | F82: P0 | G82: Integrity | H82: Every order has a valid customer and at least one line item (no orphans) | I82: Test DB seeded via sql/setup; read-only account; run after the related UI/API tests | J82: 1. Query orders with no matching customer 2. Query orders with no order lines 3. Query order lines with no parent order | K82: Tables: Orders, OrderItems, Customers | L82: 0 rows returned for each check (no violations) | M82: sql/validation/order_integrity.sql | N82: Planned | O82: Not Run
A83: T-DB-ORD-002 | B83: SQL (DB) | C83: Order Data Integrity | D83: FR-002; FR-007 | E83: FR-002-AC2; FR-007-AC4 | F83: P0 | G83: Integrity | H83: Order total equals SUM(line total) + tax - discount | I83: Test DB seeded via sql/setup; read-only account; run after the related UI/API tests | J83: 1. Join Orders to aggregated OrderItems 2. Return orders where the stored total differs from the recomputed total | K83: Tables: Orders, OrderItems | L83: 0 rows returned (difference = 0.00 for all orders) | M83: sql/validation/order_integrity.sql | N83: Planned | O83: Not Run
A84: T-DB-ORD-003 | B84: SQL (DB) | C84: Order Data Integrity | D84: FR-002 | E84: FR-002-AC7 | F84: P0 | G84: Integrity | H84: No duplicate orders exist for the same idempotency key or identical cart in a short window | I84: Test DB seeded via sql/setup; read-only account; run after the related UI/API tests | J84: 1. Group by customer + idempotency key 2. Group by customer + item set within 5 seconds 3. Return groups with count > 1 | K84: Tables: Orders, OrderItems | L84: 0 rows returned | M84: sql/validation/order_integrity.sql | N84: Planned | O84: Not Run
A85: T-DB-ORD-004 | B85: SQL (DB) | C85: Order Data Integrity | D85: FR-002 | E85: FR-002-AC5; FR-002-AC6 | F85: P0 | G85: Integrity | H85: Cancelled orders have cancel timestamps and paid orders were not modified after payment | I85: Test DB seeded via sql/setup; read-only account; run after the related UI/API tests | J85: 1. Find Cancelled orders with a null cancelled_at 2. Find orders whose modified_at is later than paid_at 3. Find cancelled orders still holding reserved stock | K85: Tables: Orders, Payments, AuditLog | L85: 0 rows returned for each check | M85: sql/validation/order_integrity.sql | N85: Planned | O85: Not Run
A86: T-DB-PAY-001 | B86: SQL (DB) | C86: Payment Data Integrity | D86: FR-003 | E86: FR-003-AC4 | F86: P0 | G86: Integrity | H86: Every paid order has exactly one successful payment | I86: Test DB seeded via sql/setup; read-only account; run after the related UI/API tests | J86: 1. Count successful payments per paid order 2. Return orders with a count other than 1 3. Return successful payments for non-paid orders | K86: Tables: Orders, Payments | L86: 0 rows returned | M86: sql/validation/payment_integrity.sql | N86: Planned | O86: Not Run
A87: T-DB-PAY-002 | B87: SQL (DB) | C87: Payment Data Integrity | D87: FR-003; FR-007 | E87: FR-003-AC2; FR-007-AC4 | F87: P0 | G87: Integrity | H87: Successful payment amount equals the order total and no payment is orphaned | I87: Test DB seeded via sql/setup; read-only account; run after the related UI/API tests | J87: 1. Compare Payments.amount to Orders.total for successful payments 2. Find payments with no order | K87: Tables: Orders, Payments | L87: 0 rows returned | M87: sql/validation/payment_integrity.sql | N87: Planned | O87: Not Run
A88: T-DB-PAY-003 | B88: SQL (DB) | C88: Payment Data Integrity | D88: FR-003 | E88: FR-003-AC3 | F88: P0 | G88: Integrity | H88: Declined payments never mark an order as paid and always store a decline reason | I88: Test DB seeded via sql/setup; read-only account; run after the related UI/API tests | J88: 1. Find declined payments whose order is Paid with no other successful payment 2. Find declined payments with a null reason code | K88: Tables: Orders, Payments | L88: 0 rows returned | M88: sql/validation/payment_integrity.sql | N88: Planned | O88: Not Run
A89: T-DB-PAY-004 | B89: SQL (DB) | C89: Payment Data Integrity | D89: FR-003; FR-005 | E89: FR-003-AC5; FR-005-AC3 | F89: P0 | G89: Integrity | H89: Refunds never exceed the amount paid and reference the original payment method | I89: Test DB seeded via sql/setup; read-only account; run after the related UI/API tests | J89: 1. SUM refunds per payment and compare with the amount paid 2. Find refunds whose method differs from the original payment method | K89: Tables: Payments, Refunds | L89: 0 rows returned | M89: sql/validation/payment_integrity.sql | N89: Planned | O89: Not Run
A90: T-DB-SHP-001 | B90: SQL (DB) | C90: Shipment Integrity | D90: FR-004 | E90: FR-004-AC1 | F90: P0 | G90: Integrity | H90: Shipments exist only for paid orders | I90: Test DB seeded via sql/setup; read-only account; run after the related UI/API tests | J90: 1. Join Shipments to Orders 2. Return shipments whose order is not paid or has no successful payment | K90: Tables: Shipments, Orders, Payments | L90: 0 rows returned | M90: sql/validation/shipment_integrity.sql | N90: Planned | O90: Not Run
A91: T-DB-SHP-002 | B91: SQL (DB) | C91: Shipment Integrity | D91: FR-004 | E91: FR-004-AC2 | F91: P0 | G91: Integrity | H91: Shipped shipments have unique, non-null tracking numbers | I91: Test DB seeded via sql/setup; read-only account; run after the related UI/API tests | J91: 1. Find Shipped/Delivered shipments with a null or empty tracking number 2. Find duplicate tracking numbers | K91: Tables: Shipments | L91: 0 rows returned | M91: sql/validation/shipment_integrity.sql | N91: Planned | O91: Not Run
A92: T-DB-SHP-003 | B92: SQL (DB) | C92: Shipment Integrity | D92: FR-004 | E92: FR-004-AC3 | F92: P0 | G92: Integrity | H92: Shipment status history follows the valid sequence with increasing timestamps | I92: Test DB seeded via sql/setup; read-only account; run after the related UI/API tests | J92: 1. Read the shipment status history ordered by timestamp 2. Find Delivered before Shipped 3. Find out-of-order timestamps | K92: Tables: ShipmentStatusHistory | L92: 0 rows returned | M92: sql/validation/shipment_integrity.sql | N92: Planned | O92: Not Run
A93: T-DB-SHP-004 | B93: SQL (DB) | C93: Shipment Integrity | D93: FR-004 | E93: FR-004-AC5 | F93: P0 | G93: Integrity | H93: Every delivered shipment has a proof-of-delivery record | I93: Test DB seeded via sql/setup; read-only account; run after the related UI/API tests | J93: 1. Find Delivered shipments with no POD row or with an empty recipient/timestamp | K93: Tables: Shipments, ProofOfDelivery | L93: 0 rows returned | M93: sql/validation/shipment_integrity.sql | N93: Planned | O93: Not Run
... A101: T-DB-AUD-004 | B101: SQL (DB) | C101: Audit & Compliance | D101: FR-007 | E101: FR-007-AC3 | F101: P0 | G101: Integrity | H101: No partially completed transactions exist (all-or-nothing) | I101: Test DB seeded via sql/setup; read-only account; run after the related UI/API tests | J101: 1. Find Paid orders with no payment 2. Find payments with no order 3. Find orders with items but with no stock ledger entry 4. Find shipments with no paid order | K101: Tables: Orders, Payments, Shipments, InventoryLedger | L101: 0 rows returned | M101: sql/validation/audit_compliance.sql | N101: Planned | O101: Not Run
A102: T-E2E-ORD-001 | B102: E2E | C102: Complete order lifecycle (login to delivery) | D102: FR-001; FR-002; FR-003; FR-004; FR-007 | E102: FR-001-AC1; FR-002-AC1; FR-002-AC2; FR-002-AC3; FR-003-AC2; FR-004-AC1; FR-004-AC2; FR-004-AC3; FR-004-AC4; FR-004-AC5; FR-007-AC1; FR-007-AC2; FR-007-AC4 | F102: P0 | G102: End-to-end | H102: Complete order lifecycle (login to delivery) | I102: Seeded test data; UI, API and DB all reachable; run after the layer suites are stable | J102: 13 steps across UI, API and SQL - see the 'E2E Steps' sheet | L102: Order is created, paid, shipped and delivered; UI, API and DB values agree at every checkpoint | M102: cypress/e2e/e2e/ + Newman + sql/validation (orchestrated) | N102: Planned | O102: Not Run
A103: T-E2E-PAY-001 | B103: E2E | C103: Payment failure and retry | D103: FR-001; FR-002; FR-003; FR-004; FR-007 | E103: FR-001-AC1; FR-002-AC1; FR-003-AC1; FR-003-AC2; FR-003-AC3; FR-003-AC4; FR-004-AC1; FR-007-AC1; FR-007-AC3; FR-007-AC4 | F103: P0 | G103: End-to-end | H103: Payment failure and retry | I103: Seeded test data; UI, API and DB all reachable; run after the layer suites are stable | J103: 11 steps across UI, API and SQL - see the 'E2E Steps' sheet | L103: A declined payment leaves no partial state; the retry succeeds once with exactly one charge | M103: cypress/e2e/e2e/ + Newman + sql/validation (orchestrated) | N103: Planned | O103: Not Run
A104: T-E2E-ADR-001 | B104: E2E | C104: Address change before delivery | D104: FR-001; FR-002; FR-003; FR-004; FR-006; FR-007 | E104: FR-001-AC1; FR-002-AC1; FR-002-AC4; FR-002-AC5; FR-003-AC2; FR-004-AC1; FR-004-AC2; FR-004-AC3; FR-006-AC3; FR-007-AC1; FR-007-AC2 | F104: P1 | G104: End-to-end | H104: Address change before delivery | I104: Seeded test data; UI, API and DB all reachable; run after the layer suites are stable | J104: 12 steps across UI, API and SQL - see the 'E2E Steps' sheet | L104: Address can be changed before payment only; the final address is consistent across UI, API, DB and the shipment | M104: cypress/e2e/e2e/ + Newman + sql/validation (orchestrated) | N104: Planned | O104: Not Run
A105: T-E2E-RET-001 | B105: E2E | C105: Return and refund processing | D105: FR-001; FR-003; FR-005; FR-007 | E105: FR-001-AC1; FR-003-AC5; FR-005-AC1; FR-005-AC2; FR-005-AC3; FR-005-AC4; FR-005-AC5; FR-007-AC1; FR-007-AC2; FR-007-AC4 | F105: P1 | G105: End-to-end | H105: Return and refund processing | I105: Seeded test data; UI, API and DB all reachable; run after the layer suites are stable | J105: 11 steps across UI, API and SQL - see the 'E2E Steps' sheet | L105: A valid return is refunded to the original method, stock is restored, the audit trail is complete, and an out-of-window return is refused | M105: cypress/e2e/e2e/ + Newman + sql/validation (orchestrated) | N105: Planned | O105: Not Run
A106: T-E2E-INV-001 | B106: E2E | C106: Inventory consistency end to end | D106: FR-002; FR-003; FR-005; FR-007 | E106: FR-002-AC1; FR-002-AC6; FR-003-AC2; FR-005-AC4; FR-007-AC1; FR-007-AC2; FR-007-AC3; FR-007-AC4 | F106: P1 | G106: End-to-end | H106: Inventory consistency end to end | I106: Seeded test data; UI, API and DB all reachable; run after the layer suites are stable | J106: 12 steps across UI, API and SQL - see the 'E2E Steps' sheet | L106: Stock moves correctly for sale, cancellation and return; ledger reconciles and UI = API = DB | M106: cypress/e2e/e2e/ + Newman + sql/validation (orchestrated) | N106: Planned | O106: Not Run

Sheet E2E Steps
A1: Scenario ID | B1: Scenario | C1: Step | D1: Layer | E1: Action | F1: Expected Result | G1: AC Ref(s) | H1: Step Result | I1: Notes / Evidence
A2: T-E2E-ORD-001 | B2: Complete order lifecycle (login to delivery) | C2: 1 | D2: UI | E2: Log in with a valid customer account | F2: Dashboard is displayed | G2: FR-001-AC1 | H2: Not Run
A3: T-E2E-ORD-001 | B3: Complete order lifecycle (login to delivery) | C3: 2 | D3: UI | E3: Add two products with valid quantities and apply a valid coupon | F3: Cart shows items, discount and total | G3: FR-002-AC1; FR-002-AC3 | H3: Not Run
A4: T-E2E-ORD-001 | B4: Complete order lifecycle (login to delivery) | C4: 3 | D4: UI | E4: Capture the displayed subtotal, discount, tax and total | F4: Values stored for comparison | G4: FR-002-AC2 | H4: Not Run
A5: T-E2E-ORD-001 | B5: Complete order lifecycle (login to delivery) | C5: 4 | D5: API | E5: GET the order/cart via API and compare with the captured UI values | F5: UI values equal API values | G5: FR-007-AC1 | H5: Not Run
A6: T-E2E-ORD-001 | B6: Complete order lifecycle (login to delivery) | C6: 5 | D6: UI | E6: Pay with a valid sandbox card | F6: Payment confirmation is displayed | G6: FR-003-AC2 | H6: Not Run
A7: T-E2E-ORD-001 | B7: Complete order lifecycle (login to delivery) | C7: 6 | D7: API | E7: GET the payment by order id | F7: Status Settled/Authorized; amount equals order total | G7: FR-003-AC2; FR-007-AC1 | H7: Not Run
A8: T-E2E-ORD-001 | B8: Complete order lifecycle (login to delivery) | C8: 7 | D8: SQL | E8: Query Orders and Payments for the order | F8: Order = Paid; exactly one successful payment; Orders.total = Payments.amount = UI total | G8: FR-007-AC2; FR-007-AC4 | H8: Not Run
A9: T-E2E-ORD-001 | B9: Complete order lifecycle (login to delivery) | C9: 8 | D9: API | E9: GET the shipment for the order | F9: Shipment created after payment; tracking number assigned | G9: FR-004-AC1; FR-004-AC2 | H9: Not Run
A10: T-E2E-ORD-001 | B10: Complete order lifecycle (login to delivery) | C10: 9 | D10: SQL | E10: Query Shipments and Inventory | F10: Shipment row exists with a unique tracking number; stock reduced by the ordered quantities | G10: FR-004-AC1; FR-007-AC2 | H10: Not Run
A11: T-E2E-ORD-001 | B11: Complete order lifecycle (login to delivery) | C11: 10 | D11: API | E11: Update the shipment to Shipped, then Delivered with proof of delivery | F11: Statuses update in order; POD stored | G11: FR-004-AC3; FR-004-AC5 | H11: Not Run
A12: T-E2E-ORD-001 | B12: Complete order lifecycle (login to delivery) | C12: 11 | D12: SQL | E12: Query NotificationLog and ProofOfDelivery | F12: SMS/email logged for Shipped and Delivered; POD record exists | G12: FR-004-AC4; FR-004-AC5 | H12: Not Run
A13: T-E2E-ORD-001 | B13: Complete order lifecycle (login to delivery) | C13: 12 | D13: UI | E13: Open the order details page | F13: Status Delivered, tracking number and POD displayed and equal to API values | G13: FR-004-AC3; FR-007-AC1 | H13: Not Run
... A60: T-E2E-INV-001 | B60: Inventory consistency end to end | C60: 12 | D60: SQL | E60: Run the reconciliation query (opening + SUM(ledger) = current) and check for negative stock | F60: No differences; no negative stock; UI = API = DB | G60: FR-007-AC3; FR-007-AC4 | H60: Not Run

Sheet RTM
A1: Requirements Traceability Matrix (Requirement > Test > Defect)
A2: Mapped test IDs are fixed text; counts, coverage and results are formulas reading 'Test Cases'. Yellow columns are for you to fill in.
A4: FR ID | B4: Functional Requirement | C4: AC ID | D4: Acceptance Criterion | E4: Cypress (UI) Tests | F4: Postman (API) Tests | G4: SQL (DB) Tests | H4: E2E Scenarios | I4: # UI | J4: # API | K4: # SQL | L4: # E2E | M4: Total Tests | N4: Coverage | O4: Passed | P4: Failed | Q4: Result | R4: Defect IDs | S4: JIRA Story / Epic | T4: Required Evidence (from brief)
A5: FR-001 | B5: User Authentication & Session Management | C5: FR-001-AC1 | D5: Valid email + password login succeeds | E5: UI-AUTH-001, UI-XBR-001, UI-XBR-002, UI-XBR-003 | F5: API-AUTH-001 | H5: E2E-ORD-001, E2E-PAY-001, E2E-ADR-001, E2E-RE001 | I5: =COUNTIFS('Test Cases'!$E$2:$E$106,"*"&$C5&"*",'Test Cases'!$B$2:$B$106,"Cypress (UI)") -> 4 | J5: =COUNTIFS('Test Cases'!$E$2:$E$106,"*"&$C5&"*",'Test Cases'!$B$2:$B$106,"Postman (API)") -> 1 | K5: =COUNTIFS('Test Cases'!$E$2:$E$106,"*"&$C5&"*",'Test Cases'!$B$2:$B$106,"SQL (DB)") -> 0 | L5: =COUNTIFS('Test Cases'!$E$2:$E$106,"*"&$C5&"*",'Test Cases'!$B$2:$B$106,"E2E") -> 4 | M5: =SUM(I5:L5) -> 9 | N5: =IF(M5=0,"NOT COVERED","Covered") -> Covered | O5: =COUNTIFS('Test Cases'!$E$2:$E$106,"*"&$C5&"*",'Test Cases'!$O$2:$O$106,"Pass") -> 0 | P5: =COUNTIFS('Test Cases'!$E$2:$E$106,"*"&$C5&"*",'Test Cases'!$O$2:$O$106,"Fail") -> 0 | Q5: =IF(M5=0,"-",IF(P5>0,"FAIL",IF(O5=M5,"PASS",IF(O5=0,"NOT RUN","IN PROGRESS")))) -> NOT RUN | T5: Cypress test results + JWT/Session token validation
A6: FR-001 | B6: User Authentication & Session Management | C6: FR-001-AC2 | D6: Invalid credentials rejected with clear error | E6: UI-AUTH-002 | F6: API-AUTH-002, API-ERR-001 | I6: =COUNTIFS('Test Cases'!$E$2:$E$106,"*"&$C6&"*",'Test Cases'!$B$2:$B$106,"Cypress (UI)") -> 1 | J6: =COUNTIFS('Test Cases'!$E$2:$E$106,"*"&$C6&"*",'Test Cases'!$B$2:$B$106,"Postman (API)") -> 2 | K6: =COUNTIFS('Test Cases'!$E$2:$E$106,"*"&$C6&"*",'Test Cases'!$B$2:$B$106,"SQL (DB)") -> 0 | L6: =COUNTIFS('Test Cases'!$E$2:$E$106,"*"&$C6&"*",'Test Cases'!$B$2:$B$106,"E2E") -> 0 | M6: =SUM(I6:L6) -> 3 | N6: =IF(M6=0,"NOT COVERED","Covered") -> Covered | O6: =COUNTIFS('Test Cases'!$E$2:$E$106,"*"&$C6&"*",'Test Cases'!$O$2:$O$106,"Pass") -> 0 | P6: =COUNTIFS('Test Cases'!$E$2:$E$106,"*"&$C6&"*",'Test Cases'!$O$2:$O$106,"Fail") -> 0 | Q6: =IF(M6=0,"-",IF(P6>0,"FAIL",IF(O6=M6,"PASS",IF(O6=0,"NOT RUN","IN PROGRESS")))) -> NOT RUN | T6: Cypress test results + JWT/Session token validation
A7: FR-001 | B7: User Authentication & Session Management | C7: FR-001-AC3 | D7: Session persists across page navigation | E7: UI-AUTH-003, UI-XBR-001, UI-XBR-002, UI-XBR-003 | F7: API-AUTH-001 | I7: =COUNTIFS('Test Cases'!$E$2:$E$106,"*"&$C7&"*",'Test Cases'!$B$2:$B$106,"Cypress (UI)") -> 4 | J7: =COUNTIFS('Test Cases'!$E$2:$E$106,"*"&$C7&"*",'Test Cases'!$B$2:$B$106,"Postman (API)") -> 1 | K7: =COUNTIFS('Test Cases'!$E$2:$E$106,"*"&$C7&"*",'Test Cases'!$B$2:$B$106,"SQL (DB)") -> 0 | L7: =COUNTIFS('Test Cases'!$E$2:$E$106,"*"&$C7&"*",'Test Cases'!$B$2:$B$106,"E2E") -> 0 | M7: =SUM(I7:L7) -> 5 | N7: =IF(M7=0,"NOT COVERED","Covered") -> Covered | O7: =COUNTIFS('Test Cases'!$E$2:$E$106,"*"&$C7&"*",'Test Cases'!$O$2:$O$106,"Pass") -> 0 | P7: =COUNTIFS('Test Cases'!$E$2:$E$106,"*"&$C7&"*",'Test Cases'!$O$2:$O$106,"Fail") -> 0 | Q7: =IF(M7=0,"-",IF(P7>0,"FAIL",IF(O7=M7,"PASS",IF(O7=0,"NOT RUN","IN PROGRESS")))) -> NOT RUN | T7: Cypress test results + JWT/Session token validation
A8: FR-001 | B8: User Authentication & Session Management | C8: FR-001-AC4 | D8: Session expires after 30 minutes of inactivity | E8: UI-AUTH-004 | I8: =COUNTIFS('Test Cases'!$E$2:$E$106,"*"&$C8&"*",'Test Cases'!$B$2:$B$106,"Cypress (UI)") -> 1 | J8: =COUNTIFS('Test Cases'!$E$2:$E$106,"*"&$C8&"*",'Test Cases'!$B$2:$B$106,"Postman (API)") -> 0 | K8: =COUNTIFS('Test Cases'!$E$2:$E$106,"*"&$C8&"*",'Test Cases'!$B$2:$B$106,"SQL (DB)") -> 0 | L8: =COUNTIFS('Test Cases'!$E$2:$E$106,"*"&$C8&"*",'Test Cases'!$B$2:$B$106,"E2E") -> 0 | M8: =SUM(I8:L8) -> 1 | N8: =IF(M8=0,"NOT COVERED","Covered") -> Covered | O8: =COUNTIFS('Test Cases'!$E$2:$E$106,"*"&$C8&"*",'Test Cases'!$O$2:$O$106,"Pass") -> 0 | P8: =COUNTIFS('Test Cases'!$E$2:$E$106,"*"&$C8&"*",'Test Cases'!$O$2:$O$106,"Fail") -> 0 | Q8: =IF(M8=0,"-",IF(P8>0,"FAIL",IF(O8=M8,"PASS",IF(O8=0,"NOT RUN","IN PROGRESS")))) -> NOT RUN | T8: Cypress test results + JWT/Session token validation
A9: FR-001 | B9: User Authentication & Session Management | C9: FR-001-AC5 | D9: User can logout, invalidating session | F9: API-AUTH-003 | I9: =COUNTIFS('Test Cases'!$E$2:$E$106,"*"&$C9&"*",'Test Cases'!$B$2:$B$106,"Cypress (UI)") -> 0 | J9: =COUNTIFS('Test Cases'!$E$2:$E$106,"*"&$C9&"*",'Test Cases'!$B$2:$B$106,"Postman (API)") -> 1 | K9: =COUNTIFS('Test Cases'!$E$2:$E$106,"*"&$C9&"*",'Test Cases'!$B$2:$B$106,"SQL (DB)") -> 0 | L9: =COUNTIFS('Test Cases'!$E$2:$E$106,"*"&$C9&"*",'Test Cases'!$B$2:$B$106,"E2E") -> 0 | M9: =SUM(I9:L9) -> 1 | N9: =IF(M9=0,"NOT COVERED","Covered") -> Covered | O9: =COUNTIFS('Test Cases'!$E$2:$E$106,"*"&$C9&"*",'Test Cases'!$O$2:$O$106,"Pass") -> 0 | P9: =COUNTIFS('Test Cases'!$E$2:$E$106,"*"&$C9&"*",'Test Cases'!$O$2:$O$106,"Fail") -> 0 | Q9: =IF(M9=0,"-",IF(P9>0,"FAIL",IF(O9=M9,"PASS",IF(O9=0,"NOT RUN","IN PROGRESS")))) -> NOT RUN | T9: Cypress test results + JWT/Session token validation
A10: FR-001 | B10: User Authentication & Session Management | C10: FR-001-AC6 | D10: Password reset via email link works | F10: API-AUTH-004 | I10: =COUNTIFS('Test Cases'!$E$2:$E$106,"*"&$C10&"*",'Test Cases'!$B$2:$B$106,"Cypress (UI)") -> 0 | J10: =COUNTIFS('Test Cases'!$E$2:$E$106,"*"&$C10&"*",'Test Cases'!$B$2:$B$106,"Postman (API)") -> 1 | K10: =COUNTIFS('Test Cases'!$E$2:$E$106,"*"&$C10&"*",'Test Cases'!$B$2:$B$106,"SQL (DB)") -> 0 | L10: =COUNTIFS('Test Cases'!$E$2:$E$106,"*"&$C10&"*",'Test Cases'!$B$2:$B$106,"E2E") -> 0 | M10: =SUM(I10:L10) -> 1 | N10: =IF(M10=0,"NOT COVERED","Covered") -> Covered | O10: =COUNTIFS('Test Cases'!$E$2:$E$106,"*"&$C10&"*",'Test Cases'!$O$2:$O$106,"Pass") -> 0 | P10: =COUNTIFS('Test Cases'!$E$2:$E$106,"*"&$C10&"*",'Test Cases'!$O$2:$O$106,"Fail") -> 0 | Q10: =IF(M10=0,"-",IF(P10>0,"FAIL",IF(O10=M10,"PASS",IF(O10=0,"NOT RUN","IN PROGRESS")))) -> NOT RUN | T10: Cypress test results + JWT/Session token validation
A11: FR-001 | B11: User Authentication & Session Management | C11: FR-001-AC7 | D11: Account lockout after 5 failed attempts | F11: API-AUTH-002 | I11: =COUNTIFS('Test Cases'!$E$2:$E$106,"*"&$C11&"*",'Test Cases'!$B$2:$B$106,"Cypress (UI)") -> 0 | J11: =COUNTIFS('Test Cases'!$E$2:$E$106,"*"&$C11&"*",'Test Cases'!$B$2:$B$106,"Postman (API)") -> 1 | K11: =COUNTIFS('Test Cases'!$E$2:$E$106,"*"&$C11&"*",'Test Cases'!$B$2:$B$106,"SQL (DB)") -> 0 | L11: =COUNTIFS('Test Cases'!$E$2:$E$106,"*"&$C11&"*",'Test Cases'!$B$2:$B$106,"E2E") -> 0 | M11: =SUM(I11:L11) -> 1 | N11: =IF(M11=0,"NOT COVERED","Covered") -> Covered | O11: =COUNTIFS('Test Cases'!$E$2:$E$106,"*"&$C11&"*",'Test Cases'!$O$2:$O$106,"Pass") -> 0 | P11: =COUNTIFS('Test Cases'!$E$2:$E$106,"*"&$C11&"*",'Test Cases'!$O$2:$O$106,"Fail") -> 0 | Q11: =IF(M11=0,"-",IF(P11>0,"FAIL",IF(O11=M11,"PASS",IF(O11=0,"NOT RUN","IN PROGRESS")))) -> NOT RUN | T11: Cypress test results + JWT/Session token validation
A12: FR-002 | B12: Order Management | C12: FR-002-AC1 | D12: Add products to order with quantity validation | E12: UI-ORD-001, UI-ORD-002 | F12: API-ORD-001, API-ORD-002, API-ERR-002 | G12: DB-INV-001 | H12: E2E-ORD-001, E2E-PAY-001, E2E-ADR-001, E2E-INV-001 | I12: =COUNTIFS('Test Cases'!$E$2:$E$106,"*"&$C12&"*",'Test Cases'!$B$2:$B$106,"Cypress (UI)") -> 2 | J12: =COUNTIFS('Test Cases'!$E$2:$E$106,"*"&$C12&"*",'Test Cases'!$B$2:$B$106,"Postman (API)") -> 3 | K12: =COUNTIFS('Test Cases'!$E$2:$E$106,"*"&$C12&"*",'Test Cases'!$B$2:$B$106,"SQL (DB)") -> 1 | L12: =COUNTIFS('Test Cases'!$E$2:$E$106,"*"&$C12&"*",'Test Cases'!$B$2:$B$106,"E2E") -> 4 | M12: =SUM(I12:L12) -> 10 | N12: =IF(M12=0,"NOT COVERED","Covered") -> Covered | O12: =COUNTIFS('Test Cases'!$E$2:$E$106,"*"&$C12&"*",'Test Cases'!$O$2:$O$106,"Pass") -> 0 | P12: =COUNTIFS('Test Cases'!$E$2:$E$106,"*"&$C12&"*",'Test Cases'!$O$2:$O$106,"Fail") -> 0 | Q12: =IF(M12=0,"-",IF(P12>0,"FAIL",IF(O12=M12,"PASS",IF(O12=0,"NOT RUN","IN PROGRESS")))) -> NOT RUN | T12: UI automation logs + SQL Order Integrity queries
A13: FR-002 | B13: Order Management | C13: FR-002-AC2 | D13: Calculate order total (items x price + tax) | E13: UI-ORD-003, UI-XBR-004, UI-XBR-005 | F13: API-ORD-003 | G13: DB-ORD-002 | H13: E2E-ORD-001 | I13: =COUNTIFS('Test Cases'!$E$2:$E$106,"*"&$C13&"*",'Test Cases'!$B$2:$B$106,"Cypress (UI)") -> 3 | J13: =COUNTIFS('Test Cases'!$E$2:$E$106,"*"&$C13&"*",'Test Cases'!$B$2:$B$106,"Postman (API)") -> 1 | K13: =COUNTIFS('Test Cases'!$E$2:$E$106,"*"&$C13&"*",'Test Cases'!$B$2:$B$106,"SQL (DB)") -> 1 | L13: =COUNTIFS('Test Cases'!$E$2:$E$106,"*"&$C13&"*",'Test Cases'!$B$2:$B$106,"E2E") -> 1 | M13: =SUM(I13:L13) -> 6 | N13: =IF(M13=0,"NOT COVERED","Covered") -> Covered | O13: =COUNTIFS('Test Cases'!$E$2:$E$106,"*"&$C13&"*",'Test Cases'!$O$2:$O$106,"Pass") -> 0 | P13: =COUNTIFS('Test Cases'!$E$2:$E$106,"*"&$C13&"*",'Test Cases'!$O$2:$O$106,"Fail") -> 0 | Q13: =IF(M13=0,"-",IF(P13>0,"FAIL",IF(O13=M13,"PASS",IF(O13=0,"NOT RUN","IN PROGRESS")))) -> NOT RUN | T13: UI automation logs + SQL Order Integrity queries
A14: FR-002 | B14: Order Management | C14: FR-002-AC3 | D14: Apply valid coupon codes for discounts | E14: UI-ORD-004, UI-ORD-005 | F14: API-ORD-004, API-ORD-005 | H14: E2E-ORD-001 | I14: =COUNTIFS('Test Cases'!$E$2:$E$106,"*"&$C14&"*",'Test Cases'!$B$2:$B$106,"Cypress (UI)") -> 2 | J14: =COUNTIFS('Test Cases'!$E$2:$E$106,"*"&$C14&"*",'Test Cases'!$B$2:$B$106,"Postman (API)") -> 2 | K14: =COUNTIFS('Test Cases'!$E$2:$E$106,"*"&$C14&"*",'Test Cases'!$B$2:$B$106,"SQL (DB)") -> 0 | L14: =COUNTIFS('Test Cases'!$E$2:$E$106,"*"&$C14&"*",'Test Cases'!$B$2:$B$106,"E2E") -> 1 | M14: =SUM(I14:L14) -> 5 | N14: =IF(M14=0,"NOT COVERED","Covered") -> Covered | O14: =COUNTIFS('Test Cases'!$E$2:$E$106,"*"&$C14&"*",'Test Cases'!$O$2:$O$106,"Pass") -> 0 | P14: =COUNTIFS('Test Cases'!$E$2:$E$106,"*"&$C14&"*",'Test Cases'!$O$2:$O$106,"Fail") -> 0 | Q14: =IF(M14=0,"-",IF(P14>0,"FAIL",IF(O14=M14,"PASS",IF(O14=0,"NOT RUN","IN PROGRESS")))) -> NOT RUN | T14: UI automation logs + SQL Order Integrity queries
A15: FR-002 | B15: Order Management | C15: FR-002-AC4 | D15: Modify order pre-payment (change quantity, address) | E15: UI-ORD-006, UI-ORD-007 | F15: API-ORD-006 | H15: E2E-ADR-001 | I15: =COUNTIFS('Test Cases'!$E$2:$E$106,"*"&$C15&"*",'Test Cases'!$B$2:$B$106,"Cypress (UI)") -> 2 | J15: =COUNTIFS('Test Cases'!$E$2:$E$106,"*"&$C15&"*",'Test Cases'!$B$2:$B$106,"Postman (API)") -> 1 | K15: =COUNTIFS('Test Cases'!$E$2:$E$106,"*"&$C15&"*",'Test Cases'!$B$2:$B$106,"SQL (DB)") -> 0 | L15: =COUNTIFS('Test Cases'!$E$2:$E$106,"*"&$C15&"*",'Test Cases'!$B$2:$B$106,"E2E") -> 1 | M15: =SUM(I15:L15) -> 4 | N15: =IF(M15=0,"NOT COVERED","Covered") -> Covered | O15: =COUNTIFS('Test Cases'!$E$2:$E$106,"*"&$C15&"*",'Test Cases'!$O$2:$O$106,"Pass") -> 0 | P15: =COUNTIFS('Test Cases'!$E$2:$E$106,"*"&$C15&"*",'Test Cases'!$O$2:$O$106,"Fail") -> 0 | Q15: =IF(M15=0,"-",IF(P15>0,"FAIL",IF(O15=M15,"PASS",IF(O15=0,"NOT RUN","IN PROGRESS")))) -> NOT RUN | T15: UI automation logs + SQL Order Integrity queries
A16: FR-002 | B16: Order Management | C16: FR-002-AC5 | D16: Cannot modify order post-payment | E16: UI-ORD-008 | F16: API-ORD-007 | G16: DB-ORD-004 | H16: E2E-ADR-001 | I16: =COUNTIFS('Test Cases'!$E$2:$E$106,"*"&$C16&"*",'Test Cases'!$B$2:$B$106,"Cypress (UI)") -> 1 | J16: =COUNTIFS('Test Cases'!$E$2:$E$106,"*"&$C16&"*",'Test Cases'!$B$2:$B$106,"Postman (API)") -> 1 | K16: =COUNTIFS('Test Cases'!$E$2:$E$106,"*"&$C16&"*",'Test Cases'!$B$2:$B$106,"SQL (DB)") -> 1 | L16: =COUNTIFS('Test Cases'!$E$2:$E$106,"*"&$C16&"*",'Test Cases'!$B$2:$B$106,"E2E") -> 1 | M16: =SUM(I16:L16) -> 4 | N16: =IF(M16=0,"NOT COVERED","Covered") -> Covered | O16: =COUNTIFS('Test Cases'!$E$2:$E$106,"*"&$C16&"*",'Test Cases'!$O$2:$O$106,"Pass") -> 0 | P16: =COUNTIFS('Test Cases'!$E$2:$E$106,"*"&$C16&"*",'Test Cases'!$O$2:$O$106,"Fail") -> 0 | Q16: =IF(M16=0,"-",IF(P16>0,"FAIL",IF(O16=M16,"PASS",IF(O16=0,"NOT RUN","IN PROGRESS")))) -> NOT RUN | T16: UI automation logs + SQL Order Integrity queries
A17: FR-002 | B17: Order Management | C17: FR-002-AC6 | D17: Cancel order returns inventory | E17: UI-ORD-009 | F17: API-ORD-008 | G17: DB-ORD-004, DB-INV-003 | H17: E2E-INV-001 | I17: =COUNTIFS('Test Cases'!$E$2:$E$106,"*"&$C17&"*",'Test Cases'!$B$2:$B$106,"Cypress (UI)") -> 1 | J17: =COUNTIFS('Test Cases'!$E$2:$E$106,"*"&$C17&"*",'Test Cases'!$B$2:$B$106,"Postman (API)") -> 1 | K17: =COUNTIFS('Test Cases'!$E$2:$E$106,"*"&$C17&"*",'Test Cases'!$B$2:$B$106,"SQL (DB)") -> 2 | L17: =COUNTIFS('Test Cases'!$E$2:$E$106,"*"&$C17&"*",'Test Cases'!$B$2:$B$106,"E2E") -> 1 | M17: =SUM(I17:L17) -> 5 | N17: =IF(M17=0,"NOT COVERED","Covered") -> Covered | O17: =COUNTIFS('Test Cases'!$E$2:$E$106,"*"&$C17&"*",'Test Cases'!$O$2:$O$106,"Pass") -> 0 | P17: =COUNTIFS('Test Cases'!$E$2:$E$106,"*"&$C17&"*",'Test Cases'!$O$2:$O$106,"Fail") -> 0 | Q17: =IF(M17=0,"-",IF(P17>0,"FAIL",IF(O17=M17,"PASS",IF(O17=0,"NOT RUN","IN PROGRESS")))) -> NOT RUN | T17: UI automation logs + SQL Order Integrity queries
A18: FR-002 | B18: Order Management | C18: FR-002-AC7 | D18: Idempotency (no duplicate orders) | E18: UI-ORD-010 | F18: API-ORD-009, API-ERR-003 | G18: DB-ORD-003 | I18: =COUNTIFS('Test Cases'!$E$2:$E$106,"*"&$C18&"*",'Test Cases'!$B$2:$B$106,"Cypress (UI)") -> 1 | J18: =COUNTIFS('Test Cases'!$E$2:$E$106,"*"&$C18&"*",'Test Cases'!$B$2:$B$106,"Postman (API)") -> 2 | K18: =COUNTIFS('Test Cases'!$E$2:$E$106,"*"&$C18&"*",'Test Cases'!$B$2:$B$106,"SQL (DB)") -> 1 | L18: =COUNTIFS('Test Cases'!$E$2:$E$106,"*"&$C18&"*",'Test Cases'!$B$2:$B$106,"E2E") -> 0 | M18: =SUM(I18:L18) -> 4 | N18: =IF(M18=0,"NOT COVERED","Covered") -> Covered | O18: =COUNTIFS('Test Cases'!$E$2:$E$106,"*"&$C18&"*",'Test Cases'!$O$2:$O$106,"Pass") -> 0 | P18: =COUNTIFS('Test Cases'!$E$2:$E$106,"*"&$C18&"*",'Test Cases'!$O$2:$O$106,"Fail") -> 0 | Q18: =IF(M18=0,"-",IF(P18>0,"FAIL",IF(O18=M18,"PASS",IF(O18=0,"NOT RUN","IN PROGRESS")))) -> NOT RUN | T18: UI automation logs + SQL Order Integrity queries
A19: FR-003 | B19: Payment Processing | C19: FR-003-AC1 | D19: Credit card validation (format, expiry, CVV) | E19: UI-PAY-002, UI-PAY-003, UI-PAY-004 | F19: API-PAY-002, API-PAY-003, API-PAY-004 | H19: E2E-PAY-001 | I19: =COUNTIFS('Test Cases'!$E$2:$E$106,"*"&$C19&"*",'Test Cases'!$B$2:$B$106,"Cypress (UI)") -> 3 | J19: =COUNTIFS('Test Cases'!$E$2:$E$106,"*"&$C19&"*",'Test Cases'!$B$2:$B$106,"Postman (API)") -> 3 | K19: =COUNTIFS('Test Cases'!$E$2:$E$106,"*"&$C19&"*",'Test Cases'!$B$2:$B$106,"SQL (DB)") -> 0 | L19: =COUNTIFS('Test Cases'!$E$2:$E$106,"*"&$C19&"*",'Test Cases'!$B$2:$B$106,"E2E") -> 1 | M19: =SUM(I19:L19) -> 7 | N19: =IF(M19=0,"NOT COVERED","Covered") -> Covered | O19: =COUNTIFS('Test Cases'!$E$2:$E$106,"*"&$C19&"*",'Test Cases'!$O$2:$O$106,"Pass") -> 0 | P19: =COUNTIFS('Test Cases'!$E$2:$E$106,"*"&$C19&"*",'Test Cases'!$O$2:$O$106,"Fail") -> 0 | Q19: =IF(M19=0,"-",IF(P19>0,"FAIL",IF(O19=M19,"PASS",IF(O19=0,"NOT RUN","IN PROGRESS")))) -> NOT RUN | T19: Transaction status records + Payment ledger SQL verification
A20: FR-003 | B20: Payment Processing | C20: FR-003-AC2 | D20: Payment authorization succeeds for valid cards | E20: UI-PAY-001 | F20: API-PAY-001 | G20: DB-PAY-002 | H20: E2E-ORD-001, E2E-PAY-001, E2E-ADR-001, E2E-INV-001 | I20: =COUNTIFS('Test Cases'!$E$2:$E$106,"*"&$C20&"*",'Test Cases'!$B$2:$B$106,"Cypress (UI)") -> 1 | J20: =COUNTIFS('Test Cases'!$E$2:$E$106,"*"&$C20&"*",'Test Cases'!$B$2:$B$106,"Postman (API)") -> 1 | K20: =COUNTIFS('Test Cases'!$E$2:$E$106,"*"&$C20&"*",'Test Cases'!$B$2:$B$106,"SQL (DB)") -> 1 | L20: =COUNTIFS('Test Cases'!$E$2:$E$106,"*"&$C20&"*",'Test Cases'!$B$2:$B$106,"E2E") -> 4 | M20: =SUM(I20:L20) -> 7 | N20: =IF(M20=0,"NOT COVERED","Covered") -> Covered | O20: =COUNTIFS('Test Cases'!$E$2:$E$106,"*"&$C20&"*",'Test Cases'!$O$2:$O$106,"Pass") -> 0 | P20: =COUNTIFS('Test Cases'!$E$2:$E$106,"*"&$C20&"*",'Test Cases'!$O$2:$O$106,"Fail") -> 0 | Q20: =IF(M20=0,"-",IF(P20>0,"FAIL",IF(O20=M20,"PASS",IF(O20=0,"NOT RUN","IN PROGRESS")))) -> NOT RUN | T20: Transaction status records + Payment ledger SQL verification
A21: FR-003 | B21: Payment Processing | C21: FR-003-AC3 | D21: Payment declined gracefully for invalid cards | E21: UI-PAY-005 | F21: API-PAY-005 | G21: DB-PAY-003 | H21: E2E-PAY-001 | I21: =COUNTIFS('Test Cases'!$E$2:$E$106,"*"&$C21&"*",'Test Cases'!$B$2:$B$106,"Cypress (UI)") -> 1 | J21: =COUNTIFS('Test Cases'!$E$2:$E$106,"*"&$C21&"*",'Test Cases'!$B$2:$B$106,"Postman (API)") -> 1 | K21: =COUNTIFS('Test Cases'!$E$2:$E$106,"*"&$C21&"*",'Test Cases'!$B$2:$B$106,"SQL (DB)") -> 1 | L21: =COUNTIFS('Test Cases'!$E$2:$E$106,"*"&$C21&"*",'Test Cases'!$B$2:$B$106,"E2E") -> 1 | M21: =SUM(I21:L21) -> 4 | N21: =IF(M21=0,"NOT COVERED","Covered") -> Covered | O21: =COUNTIFS('Test Cases'!$E$2:$E$106,"*"&$C21&"*",'Test Cases'!$O$2:$O$106,"Pass") -> 0 | P21: =COUNTIFS('Test Cases'!$E$2:$E$106,"*"&$C21&"*",'Test Cases'!$O$2:$O$106,"Fail") -> 0 | Q21: =IF(M21=0,"-",IF(P21>0,"FAIL",IF(O21=M21,"PASS",IF(O21=0,"NOT RUN","IN PROGRESS")))) -> NOT RUN | T21: Transaction status records + Payment ledger SQL verification
A22: FR-003 | B22: Payment Processing | C22: FR-003-AC4 | D22: No double-charging (duplicate prevention) | E22: UI-PAY-006 | F22: API-PAY-006 | G22: DB-PAY-001 | H22: E2E-PAY-001 | I22: =COUNTIFS('Test Cases'!$E$2:$E$106,"*"&$C22&"*",'Test Cases'!$B$2:$B$106,"Cypress (UI)") -> 1 | J22: =COUNTIFS('Test Cases'!$E$2:$E$106,"*"&$C22&"*",'Test Cases'!$B$2:$B$106,"Postman (API)") -> 1 | K22: =COUNTIFS('Test Cases'!$E$2:$E$106,"*"&$C22&"*",'Test Cases'!$B$2:$B$106,"SQL (DB)") -> 1 | L22: =COUNTIFS('Test Cases'!$E$2:$E$106,"*"&$C22&"*",'Test Cases'!$B$2:$B$106,"E2E") -> 1 | M22: =SUM(I22:L22) -> 4 | N22: =IF(M22=0,"NOT COVERED","Covered") -> Covered | O22: =COUNTIFS('Test Cases'!$E$2:$E$106,"*"&$C22&"*",'Test Cases'!$O$2:$O$106,"Pass") -> 0 | P22: =COUNTIFS('Test Cases'!$E$2:$E$106,"*"&$C22&"*",'Test Cases'!$O$2:$O$106,"Fail") -> 0 | Q22: =IF(M22=0,"-",IF(P22>0,"FAIL",IF(O22=M22,"PASS",IF(O22=0,"NOT RUN","IN PROGRESS")))) -> NOT RUN | T22: Transaction status records + Payment ledger SQL verification
A23: FR-003 | B23: Payment Processing | C23: FR-003-AC5 | D23: Refund functionality works correctly | F23: API-PAY-007, API-PAY-008 | G23: DB-PAY-004 | H23: E2E-RE001 | I23: =COUNTIFS('Test Cases'!$E$2:$E$106,"*"&$C23&"*",'Test Cases'!$B$2:$B$106,"Cypress (UI)") -> 0 | J23: =COUNTIFS('Test Cases'!$E$2:$E$106,"*"&$C23&"*",'Test Cases'!$B$2:$B$106,"Postman (API)") -> 2 | K23: =COUNTIFS('Test Cases'!$E$2:$E$106,"*"&$C23&"*",'Test Cases'!$B$2:$B$106,"SQL (DB)") -> 1 | L23: =COUNTIFS('Test Cases'!$E$2:$E$106,"*"&$C23&"*",'Test Cases'!$B$2:$B$106,"E2E") -> 1 | M23: =SUM(I23:L23) -> 4 | N23: =IF(M23=0,"NOT COVERED","Covered") -> Covered | O23: =COUNTIFS('Test Cases'!$E$2:$E$106,"*"&$C23&"*",'Test Cases'!$O$2:$O$106,"Pass") -> 0 | P23: =COUNTIFS('Test Cases'!$E$2:$E$106,"*"&$C23&"*",'Test Cases'!$O$2:$O$106,"Fail") -> 0 | Q23: =IF(M23=0,"-",IF(P23>0,"FAIL",IF(O23=M23,"PASS",IF(O23=0,"NOT RUN","IN PROGRESS")))) -> NOT RUN | T23: Transaction status records + Payment ledger SQL verification
A24: FR-004 | B24: Shipment & Delivery Tracking | C24: FR-004-AC1 | D24: Shipment created after payment confirmed | E24: UI-DEL-004 | F24: API-SHP-001, API-SHP-002 | G24: DB-SHP-001 | H24: E2E-ORD-001, E2E-PAY-001, E2E-ADR-001 | I24: =COUNTIFS('Test Cases'!$E$2:$E$106,"*"&$C24&"*",'Test Cases'!$B$2:$B$106,"Cypress (UI)") -> 1 | J24: =COUNTIFS('Test Cases'!$E$2:$E$106,"*"&$C24&"*",'Test Cases'!$B$2:$B$106,"Postman (API)") -> 2 | K24: =COUNTIFS('Test Cases'!$E$2:$E$106,"*"&$C24&"*",'Test Cases'!$B$2:$B$106,"SQL (DB)") -> 1 | L24: =COUNTIFS('Test Cases'!$E$2:$E$106,"*"&$C24&"*",'Test Cases'!$B$2:$B$106,"E2E") -> 3 | M24: =SUM(I24:L24) -> 7 | N24: =IF(M24=0,"NOT COVERED","Covered") -> Covered | O24: =COUNTIFS('Test Cases'!$E$2:$E$106,"*"&$C24&"*",'Test Cases'!$O$2:$O$106,"Pass") -> 0 | P24: =COUNTIFS('Test Cases'!$E$2:$E$106,"*"&$C24&"*",'Test Cases'!$O$2:$O$106,"Fail") -> 0 | Q24: =IF(M24=0,"-",IF(P24>0,"FAIL",IF(O24=M24,"PASS",IF(O24=0,"NOT RUN","IN PROGRESS")))) -> NOT RUN | T24: Tracking status flow logs + SMS/Email notification logs
A25: FR-004 | B25: Shipment & Delivery Tracking | C25: FR-004-AC2 | D25: Tracking number assigned and visible | E25: UI-DEL-001, UI-DEL-005, UI-XBR-006 | F25: API-SHP-003, API-DEL-001 | G25: DB-SHP-002 | H25: E2E-ORD-001, E2E-ADR-001 | I25: =COUNTIFS('Test Cases'!$E$2:$E$106,"*"&$C25&"*",'Test Cases'!$B$2:$B$106,"Cypress (UI)") -> 3 | J25: =COUNTIFS('Test Cases'!$E$2:$E$106,"*"&$C25&"*",'Test Cases'!$B$2:$B$106,"Postman (API)") -> 2 | K25: =COUNTIFS('Test Cases'!$E$2:$E$106,"*"&$C25&"*",'Test Cases'!$B$2:$B$106,"SQL (DB)") -> 1 | L25: =COUNTIFS('Test Cases'!$E$2:$E$106,"*"&$C25&"*",'Test Cases'!$B$2:$B$106,"E2E") -> 2 | M25: =SUM(I25:L25) -> 8 | N25: =IF(M25=0,"NOT COVERED","Covered") -> Covered | O25: =COUNTIFS('Test Cases'!$E$2:$E$106,"*"&$C25&"*",'Test Cases'!$O$2:$O$106,"Pass") -> 0 | P25: =COUNTIFS('Test Cases'!$E$2:$E$106,"*"&$C25&"*",'Test Cases'!$O$2:$O$106,"Fail") -> 0 | Q25: =IF(M25=0,"-",IF(P25>0,"FAIL",IF(O25=M25,"PASS",IF(O25=0,"NOT RUN","IN PROGRESS")))) -> NOT RUN | T25: Tracking status flow logs + SMS/Email notification logs
A26: FR-004 | B26: Shipment & Delivery Tracking | C26: FR-004-AC3 | D26: Status updates correctly (Shipped -> Delivered) | E26: UI-DEL-002, UI-DEL-003, UI-XBR-006 | F26: API-SHP-004, API-SHP-005, API-DEL-001, API-DEL-002 | G26: DB-SHP-003 | H26: E2E-ORD-001, E2E-ADR-001 | I26: =COUNTIFS('Test Cases'!$E$2:$E$106,"*"&$C26&"*",'Test Cases'!$B$2:$B$106,"Cypress (UI)") -> 3 | J26: =COUNTIFS('Test Cases'!$E$2:$E$106,"*"&$C26&"*",'Test Cases'!$B$2:$B$106,"Postman (API)") -> 4 | K26: =COUNTIFS('Test Cases'!$E$2:$E$106,"*"&$C26&"*",'Test Cases'!$B$2:$B$106,"SQL (DB)") -> 1 | L26: =COUNTIFS('Test Cases'!$E$2:$E$106,"*"&$C26&"*",'Test Cases'!$B$2:$B$106,"E2E") -> 2 | M26: =SUM(I26:L26) -> 10 | N26: =IF(M26=0,"NOT COVERED","Covered") -> Covered | O26: =COUNTIFS('Test Cases'!$E$2:$E$106,"*"&$C26&"*",'Test Cases'!$O$2:$O$106,"Pass") -> 0 | P26: =COUNTIFS('Test Cases'!$E$2:$E$106,"*"&$C26&"*",'Test Cases'!$O$2:$O$106,"Fail") -> 0 | Q26: =IF(M26=0,"-",IF(P26>0,"FAIL",IF(O26=M26,"PASS",IF(O26=0,"NOT RUN","IN PROGRESS")))) -> NOT RUN | T26: Tracking status flow logs + SMS/Email notification logs
A27: FR-004 | B27: Shipment & Delivery Tracking | C27: FR-004-AC4 | D27: Customer notifications (SMS/Email) triggered | F27: API-SHP-006, API-DEL-004 | G27: DB-AUD-003 | H27: E2E-ORD-001 | I27: =COUNTIFS('Test Cases'!$E$2:$E$106,"*"&$C27&"*",'Test Cases'!$B$2:$B$106,"Cypress (UI)") -> 0 | J27: =COUNTIFS('Test Cases'!$E$2:$E$106,"*"&$C27&"*",'Test Cases'!$B$2:$B$106,"Postman (API)") -> 2 | K27: =COUNTIFS('Test Cases'!$E$2:$E$106,"*"&$C27&"*",'Test Cases'!$B$2:$B$106,"SQL (DB)") -> 1 | L27: =COUNTIFS('Test Cases'!$E$2:$E$106,"*"&$C27&"*",'Test Cases'!$B$2:$B$106,"E2E") -> 1 | M27: =SUM(I27:L27) -> 4 | N27: =IF(M27=0,"NOT COVERED","Covered") -> Covered | O27: =COUNTIFS('Test Cases'!$E$2:$E$106,"*"&$C27&"*",'Test Cases'!$O$2:$O$106,"Pass") -> 0 | P27: =COUNTIFS('Test Cases'!$E$2:$E$106,"*"&$C27&"*",'Test Cases'!$O$2:$O$106,"Fail") -> 0 | Q27: =IF(M27=0,"-",IF(P27>0,"FAIL",IF(O27=M27,"PASS",IF(O27=0,"NOT RUN","IN PROGRESS")))) -> NOT RUN | T27: Tracking status flow logs + SMS/Email notification logs
A28: FR-004 | B28: Shipment & Delivery Tracking | C28: FR-004-AC5 | D28: Proof of delivery (POD) recorded | E28: UI-DEL-006 | F28: API-DEL-003 | G28: DB-SHP-004 | H28: E2E-ORD-001 | I28: =COUNTIFS('Test Cases'!$E$2:$E$106,"*"&$C28&"*",'Test Cases'!$B$2:$B$106,"Cypress (UI)") -> 1 | J28: =COUNTIFS('Test Cases'!$E$2:$E$106,"*"&$C28&"*",'Test Cases'!$B$2:$B$106,"Postman (API)") -> 1 | K28: =COUNTIFS('Test Cases'!$E$2:$E$106,"*"&$C28&"*",'Test Cases'!$B$2:$B$106,"SQL (DB)") -> 1 | L28: =COUNTIFS('Test Cases'!$E$2:$E$106,"*"&$C28&"*",'Test Cases'!$B$2:$B$106,"E2E") -> 1 | M28: =SUM(I28:L28) -> 4 | N28: =IF(M28=0,"NOT COVERED","Covered") -> Covered | O28: =COUNTIFS('Test Cases'!$E$2:$E$106,"*"&$C28&"*",'Test Cases'!$O$2:$O$106,"Pass") -> 0 | P28: =COUNTIFS('Test Cases'!$E$2:$E$106,"*"&$C28&"*",'Test Cases'!$O$2:$O$106,"Fail") -> 0 | Q28: =IF(M28=0,"-",IF(P28>0,"FAIL",IF(O28=M28,"PASS",IF(O28=0,"NOT RUN","IN PROGRESS")))) -> NOT RUN | T28: Tracking status flow logs + SMS/Email notification logs
A29: FR-005 | B29: Returns & Refunds Processing | C29: FR-005-AC1 | D29: Return window enforcement (30 days) | E29: UI-RE001, UI-RE002 | F29: API-RE001, API-RE004 | H29: E2E-RE001 | I29: =COUNTIFS('Test Cases'!$E$2:$E$106,"*"&$C29&"*",'Test Cases'!$B$2:$B$106,"Cypress (UI)") -> 2 | J29: =COUNTIFS('Test Cases'!$E$2:$E$106,"*"&$C29&"*",'Test Cases'!$B$2:$B$106,"Postman (API)") -> 2 | K29: =COUNTIFS('Test Cases'!$E$2:$E$106,"*"&$C29&"*",'Test Cases'!$B$2:$B$106,"SQL (DB)") -> 0 | L29: =COUNTIFS('Test Cases'!$E$2:$E$106,"*"&$C29&"*",'Test Cases'!$B$2:$B$106,"E2E") -> 1 | M29: =SUM(I29:L29) -> 5 | N29: =IF(M29=0,"NOT COVERED","Covered") -> Covered | O29: =COUNTIFS('Test Cases'!$E$2:$E$106,"*"&$C29&"*",'Test Cases'!$O$2:$O$106,"Pass") -> 0 | P29: =COUNTIFS('Test Cases'!$E$2:$E$106,"*"&$C29&"*",'Test Cases'!$O$2:$O$106,"Fail") -> 0 | Q29: =IF(M29=0,"-",IF(P29>0,"FAIL",IF(O29=M29,"PASS",IF(O29=0,"NOT RUN","IN PROGRESS")))) -> NOT RUN | T29: Return workflow logs + Stock restoration SQL validation
A30: FR-005 | B30: Returns & Refunds Processing | C30: FR-005-AC2 | D30: Refund amount calculated correctly | E30: UI-RE003 | F30: API-RE002, API-RE004 | H30: E2E-RE001 | I30: =COUNTIFS('Test Cases'!$E$2:$E$106,"*"&$C30&"*",'Test Cases'!$B$2:$B$106,"Cypress (UI)") -> 1 | J30: =COUNTIFS('Test Cases'!$E$2:$E$106,"*"&$C30&"*",'Test Cases'!$B$2:$B$106,"Postman (API)") -> 2 | K30: =COUNTIFS('Test Cases'!$E$2:$E$106,"*"&$C30&"*",'Test Cases'!$B$2:$B$106,"SQL (DB)") -> 0 | L30: =COUNTIFS('Test Cases'!$E$2:$E$106,"*"&$C30&"*",'Test Cases'!$B$2:$B$106,"E2E") -> 1 | M30: =SUM(I30:L30) -> 4 | N30: =IF(M30=0,"NOT COVERED","Covered") -> Covered | O30: =COUNTIFS('Test Cases'!$E$2:$E$106,"*"&$C30&"*",'Test Cases'!$O$2:$O$106,"Pass") -> 0 | P30: =COUNTIFS('Test Cases'!$E$2:$E$106,"*"&$C30&"*",'Test Cases'!$O$2:$O$106,"Fail") -> 0 | Q30: =IF(M30=0,"-",IF(P30>0,"FAIL",IF(O30=M30,"PASS",IF(O30=0,"NOT RUN","IN PROGRESS")))) -> NOT RUN | T30: Return workflow logs + Stock restoration SQL validation
A31: FR-005 | B31: Returns & Refunds Processing | C31: FR-005-AC3 | D31: Refund issued to original payment method | E31: UI-RE004 | F31: API-RE003 | G31: DB-PAY-004 | H31: E2E-RE001 | I31: =COUNTIFS('Test Cases'!$E$2:$E$106,"*"&$C31&"*",'Test Cases'!$B$2:$B$106,"Cypress (UI)") -> 1 | J31: =COUNTIFS('Test Cases'!$E$2:$E$106,"*"&$C31&"*",'Test Cases'!$B$2:$B$106,"Postman (API)") -> 1 | K31: =COUNTIFS('Test Cases'!$E$2:$E$106,"*"&$C31&"*",'Test Cases'!$B$2:$B$106,"SQL (DB)") -> 1 | L31: =COUNTIFS('Test Cases'!$E$2:$E$106,"*"&$C31&"*",'Test Cases'!$B$2:$B$106,"E2E") -> 1 | M31: =SUM(I31:L31) -> 4 | N31: =IF(M31=0,"NOT COVERED","Covered") -> Covered | O31: =COUNTIFS('Test Cases'!$E$2:$E$106,"*"&$C31&"*",'Test Cases'!$O$2:$O$106,"Pass") -> 0 | P31: =COUNTIFS('Test Cases'!$E$2:$E$106,"*"&$C31&"*",'Test Cases'!$O$2:$O$106,"Fail") -> 0 | Q31: =IF(M31=0,"-",IF(P31>0,"FAIL",IF(O31=M31,"PASS",IF(O31=0,"NOT RUN","IN PROGRESS")))) -> NOT RUN | T31: Return workflow logs + Stock restoration SQL validation
A32: FR-005 | B32: Returns & Refunds Processing | C32: FR-005-AC4 | D32: Inventory restored upon return receipt | G32: DB-INV-004 | H32: E2E-RE001, E2E-INV-001 | I32: =COUNTIFS('Test Cases'!$E$2:$E$106,"*"&$C32&"*",'Test Cases'!$B$2:$B$106,"Cypress (UI)") -> 0 | J32: =COUNTIFS('Test Cases'!$E$2:$E$106,"*"&$C32&"*",'Test Cases'!$B$2:$B$106,"Postman (API)") -> 0 | K32: =COUNTIFS('Test Cases'!$E$2:$E$106,"*"&$C32&"*",'Test Cases'!$B$2:$B$106,"SQL (DB)") -> 1 | L32: =COUNTIFS('Test Cases'!$E$2:$E$106,"*"&$C32&"*",'Test Cases'!$B$2:$B$106,"E2E") -> 2 | M32: =SUM(I32:L32) -> 3 | N32: =IF(M32=0,"NOT COVERED","Covered") -> Covered | O32: =COUNTIFS('Test Cases'!$E$2:$E$106,"*"&$C32&"*",'Test Cases'!$O$2:$O$106,"Pass") -> 0 | P32: =COUNTIFS('Test Cases'!$E$2:$E$106,"*"&$C32&"*",'Test Cases'!$O$2:$O$106,"Fail") -> 0 | Q32: =IF(M32=0,"-",IF(P32>0,"FAIL",IF(O32=M32,"PASS",IF(O32=0,"NOT RUN","IN PROGRESS")))) -> NOT RUN | T32: Return workflow logs + Stock restoration SQL validation
A33: FR-005 | B33: Returns & Refunds Processing | C33: FR-005-AC5 | D33: Audit trail completeness | G33: DB-AUD-001, DB-AUD-002 | H33: E2E-RE001 | I33: =COUNTIFS('Test Cases'!$E$2:$E$106,"*"&$C33&"*",'Test Cases'!$B$2:$B$106,"Cypress (UI)") -> 0 | J33: =COUNTIFS('Test Cases'!$E$2:$E$106,"*"&$C33&"*",'Test Cases'!$B$2:$B$106,"Postman (API)") -> 0 | K33: =COUNTIFS('Test Cases'!$E$2:$E$106,"*"&$C33&"*",'Test Cases'!$B$2:$B$106,"SQL (DB)") -> 2 | L33: =COUNTIFS('Test Cases'!$E$2:$E$106,"*"&$C33&"*",'Test Cases'!$B$2:$B$106,"E2E") -> 1 | M33: =SUM(I33:L33) -> 3 | N33: =IF(M33=0,"NOT COVERED","Covered") -> Covered | O33: =COUNTIFS('Test Cases'!$E$2:$E$106,"*"&$C33&"*",'Test Cases'!$O$2:$O$106,"Pass") -> 0 | P33: =COUNTIFS('Test Cases'!$E$2:$E$106,"*"&$C33&"*",'Test Cases'!$O$2:$O$106,"Fail") -> 0 | Q33: =IF(M33=0,"-",IF(P33>0,"FAIL",IF(O33=M33,"PASS",IF(O33=0,"NOT RUN","IN PROGRESS")))) -> NOT RUN | T33: Return workflow logs + Stock restoration SQL validation
A34: FR-006 | B34: Dashboard & Account Management | C34: FR-006-AC1 | D34: Order history displays with pagination | E34: UI-DASH-001 | F34: API-ORD-010 | I34: =COUNTIFS('Test Cases'!$E$2:$E$106,"*"&$C34&"*",'Test Cases'!$B$2:$B$106,"Cypress (UI)") -> 1 | J34: =COUNTIFS('Test Cases'!$E$2:$E$106,"*"&$C34&"*",'Test Cases'!$B$2:$B$106,"Postman (API)") -> 1 | K34: =COUNTIFS('Test Cases'!$E$2:$E$106,"*"&$C34&"*",'Test Cases'!$B$2:$B$106,"SQL (DB)") -> 0 | L34: =COUNTIFS('Test Cases'!$E$2:$E$106,"*"&$C34&"*",'Test Cases'!$B$2:$B$106,"E2E") -> 0 | M34: =SUM(I34:L34) -> 2 | N34: =IF(M34=0,"NOT COVERED","Covered") -> Covered | O34: =COUNTIFS('Test Cases'!$E$2:$E$106,"*"&$C34&"*",'Test Cases'!$O$2:$O$106,"Pass") -> 0 | P34: =COUNTIFS('Test Cases'!$E$2:$E$106,"*"&$C34&"*",'Test Cases'!$O$2:$O$106,"Fail") -> 0 | Q34: =IF(M34=0,"-",IF(P34>0,"FAIL",IF(O34=M34,"PASS",IF(O34=0,"NOT RUN","IN PROGRESS")))) -> NOT RUN | T34: Dashboard UI screenshots + User profile API response logs
A35: FR-006 | B35: Dashboard & Account Management | C35: FR-006-AC2 | D35: Filter by date range, status, price | E35: UI-DASH-002 | F35: API-ORD-010 | I35: =COUNTIFS('Test Cases'!$E$2:$E$106,"*"&$C35&"*",'Test Cases'!$B$2:$B$106,"Cypress (UI)") -> 1 | J35: =COUNTIFS('Test Cases'!$E$2:$E$106,"*"&$C35&"*",'Test Cases'!$B$2:$B$106,"Postman (API)") -> 1 | K35: =COUNTIFS('Test Cases'!$E$2:$E$106,"*"&$C35&"*",'Test Cases'!$B$2:$B$106,"SQL (DB)") -> 0 | L35: =COUNTIFS('Test Cases'!$E$2:$E$106,"*"&$C35&"*",'Test Cases'!$B$2:$B$106,"E2E") -> 0 | M35: =SUM(I35:L35) -> 2 | N35: =IF(M35=0,"NOT COVERED","Covered") -> Covered | O35: =COUNTIFS('Test Cases'!$E$2:$E$106,"*"&$C35&"*",'Test Cases'!$O$2:$O$106,"Pass") -> 0 | P35: =COUNTIFS('Test Cases'!$E$2:$E$106,"*"&$C35&"*",'Test Cases'!$O$2:$O$106,"Fail") -> 0 | Q35: =IF(M35=0,"-",IF(P35>0,"FAIL",IF(O35=M35,"PASS",IF(O35=0,"NOT RUN","IN PROGRESS")))) -> NOT RUN | T35: Dashboard UI screenshots + User profile API response logs
A36: FR-006 | B36: Dashboard & Account Management | C36: FR-006-AC3 | D36: Manage saved addresses | E36: UI-DASH-003 | F36: API-ERR-004 | H36: E2E-ADR-001 | I36: =COUNTIFS('Test Cases'!$E$2:$E$106,"*"&$C36&"*",'Test Cases'!$B$2:$B$106,"Cypress (UI)") -> 1 | J36: =COUNTIFS('Test Cases'!$E$2:$E$106,"*"&$C36&"*",'Test Cases'!$B$2:$B$106,"Postman (API)") -> 1 | K36: =COUNTIFS('Test Cases'!$E$2:$E$106,"*"&$C36&"*",'Test Cases'!$B$2:$B$106,"SQL (DB)") -> 0 | L36: =COUNTIFS('Test Cases'!$E$2:$E$106,"*"&$C36&"*",'Test Cases'!$B$2:$B$106,"E2E") -> 1 | M36: =SUM(I36:L36) -> 3 | N36: =IF(M36=0,"NOT COVERED","Covered") -> Covered | O36: =COUNTIFS('Test Cases'!$E$2:$E$106,"*"&$C36&"*",'Test Cases'!$O$2:$O$106,"Pass") -> 0 | P36: =COUNTIFS('Test Cases'!$E$2:$E$106,"*"&$C36&"*",'Test Cases'!$O$2:$O$106,"Fail") -> 0 | Q36: =IF(M36=0,"-",IF(P36>0,"FAIL",IF(O36=M36,"PASS",IF(O36=0,"NOT RUN","IN PROGRESS")))) -> NOT RUN | T36: Dashboard UI screenshots + User profile API response logs
A37: FR-006 | B37: Dashboard & Account Management | C37: FR-006-AC4 | D37: Update profile (name, email, phone) | E37: UI-DASH-004 | F37: API-ERR-004 | I37: =COUNTIFS('Test Cases'!$E$2:$E$106,"*"&$C37&"*",'Test Cases'!$B$2:$B$106,"Cypress (UI)") -> 1 | J37: =COUNTIFS('Test Cases'!$E$2:$E$106,"*"&$C37&"*",'Test Cases'!$B$2:$B$106,"Postman (API)") -> 1 | K37: =COUNTIFS('Test Cases'!$E$2:$E$106,"*"&$C37&"*",'Test Cases'!$B$2:$B$106,"SQL (DB)") -> 0 | L37: =COUNTIFS('Test Cases'!$E$2:$E$106,"*"&$C37&"*",'Test Cases'!$B$2:$B$106,"E2E") -> 0 | M37: =SUM(I37:L37) -> 2 | N37: =IF(M37=0,"NOT COVERED","Covered") -> Covered | O37: =COUNTIFS('Test Cases'!$E$2:$E$106,"*"&$C37&"*",'Test Cases'!$O$2:$O$106,"Pass") -> 0 | P37: =COUNTIFS('Test Cases'!$E$2:$E$106,"*"&$C37&"*",'Test Cases'!$O$2:$O$106,"Fail") -> 0 | Q37: =IF(M37=0,"-",IF(P37>0,"FAIL",IF(O37=M37,"PASS",IF(O37=0,"NOT RUN","IN PROGRESS")))) -> NOT RUN | T37: Dashboard UI screenshots + User profile API response logs
A38: FR-007 | B38: Data Consistency & Cross-Layer Validation | C38: FR-007-AC1 | D38: UI displays data matching API response | H38: E2E-ORD-001, E2E-PAY-001, E2E-ADR-001, E2E-RE001, E2E-INV-001 | I38: =COUNTIFS('Test Cases'!$E$2:$E$106,"*"&$C38&"*",'Test Cases'!$B$2:$B$106,"Cypress (UI)") -> 0 | J38: =COUNTIFS('Test Cases'!$E$2:$E$106,"*"&$C38&"*",'Test Cases'!$B$2:$B$106,"Postman (API)") -> 0 | K38: =COUNTIFS('Test Cases'!$E$2:$E$106,"*"&$C38&"*",'Test Cases'!$B$2:$B$106,"SQL (DB)") -> 0 | L38: =COUNTIFS('Test Cases'!$E$2:$E$106,"*"&$C38&"*",'Test Cases'!$B$2:$B$106,"E2E") -> 5 | M38: =SUM(I38:L38) -> 5 | N38: =IF(M38=0,"NOT COVERED","Covered") -> Covered | O38: =COUNTIFS('Test Cases'!$E$2:$E$106,"*"&$C38&"*",'Test Cases'!$O$2:$O$106,"Pass") -> 0 | P38: =COUNTIFS('Test Cases'!$E$2:$E$106,"*"&$C38&"*",'Test Cases'!$O$2:$O$106,"Fail") -> 0 | Q38: =IF(M38=0,"-",IF(P38>0,"FAIL",IF(O38=M38,"PASS",IF(O38=0,"NOT RUN","IN PROGRESS")))) -> NOT RUN | T38: Cross-layer trace maps + Reconciliation reports
A39: FR-007 | B39: Data Consistency & Cross-Layer Validation | C39: FR-007-AC2 | D39: API response matches DB records | G39: DB-ORD-001, DB-INV-002 | H39: E2E-ORD-001, E2E-ADR-001, E2E-RE001, E2E-INV-001 | I39: =COUNTIFS('Test Cases'!$E$2:$E$106,"*"&$C39&"*",'Test Cases'!$B$2:$B$106,"Cypress (UI)") -> 0 | J39: =COUNTIFS('Test Cases'!$E$2:$E$106,"*"&$C39&"*",'Test Cases'!$B$2:$B$106,"Postman (API)") -> 0 | K39: =COUNTIFS('Test Cases'!$E$2:$E$106,"*"&$C39&"*",'Test Cases'!$B$2:$B$106,"SQL (DB)") -> 2 | L39: =COUNTIFS('Test Cases'!$E$2:$E$106,"*"&$C39&"*",'Test Cases'!$B$2:$B$106,"E2E") -> 4 | M39: =SUM(I39:L39) -> 6 | N39: =IF(M39=0,"NOT COVERED","Covered") -> Covered | O39: =COUNTIFS('Test Cases'!$E$2:$E$106,"*"&$C39&"*",'Test Cases'!$O$2:$O$106,"Pass") -> 0 | P39: =COUNTIFS('Test Cases'!$E$2:$E$106,"*"&$C39&"*",'Test Cases'!$O$2:$O$106,"Fail") -> 0 | Q39: =IF(M39=0,"-",IF(P39>0,"FAIL",IF(O39=M39,"PASS",IF(O39=0,"NOT RUN","IN PROGRESS")))) -> NOT RUN | T39: Cross-layer trace maps + Reconciliation reports
A40: FR-007 | B40: Data Consistency & Cross-Layer Validation | C40: FR-007-AC3 | D40: Transaction completeness (all-or-nothing) | G40: DB-ORD-001, DB-AUD-004 | H40: E2E-PAY-001, E2E-INV-001 | I40: =COUNTIFS('Test Cases'!$E$2:$E$106,"*"&$C40&"*",'Test Cases'!$B$2:$B$106,"Cypress (UI)") -> 0 | J40: =COUNTIFS('Test Cases'!$E$2:$E$106,"*"&$C40&"*",'Test Cases'!$B$2:$B$106,"Postman (API)") -> 0 | K40: =COUNTIFS('Test Cases'!$E$2:$E$106,"*"&$C40&"*",'Test Cases'!$B$2:$B$106,"SQL (DB)") -> 2 | L40: =COUNTIFS('Test Cases'!$E$2:$E$106,"*"&$C40&"*",'Test Cases'!$B$2:$B$106,"E2E") -> 2 | M40: =SUM(I40:L40) -> 4 | N40: =IF(M40=0,"NOT COVERED","Covered") -> Covered | O40: =COUNTIFS('Test Cases'!$E$2:$E$106,"*"&$C40&"*",'Test Cases'!$O$2:$O$106,"Pass") -> 0 | P40: =COUNTIFS('Test Cases'!$E$2:$E$106,"*"&$C40&"*",'Test Cases'!$O$2:$O$106,"Fail") -> 0 | Q40: =IF(M40=0,"-",IF(P40>0,"FAIL",IF(O40=M40,"PASS",IF(O40=0,"NOT RUN","IN PROGRESS")))) -> NOT RUN | T40: Cross-layer trace maps + Reconciliation reports
A41: FR-007 | B41: Data Consistency & Cross-Layer Validation | C41: FR-007-AC4 | D41: Balance calculations consistent (UI = API = DB) | G41: DB-ORD-002, DB-PAY-002, DB-INV-002 | H41: E2E-ORD-001, E2E-PAY-001, E2E-RE001, E2E-INV-001 | I41: =COUNTIFS('Test Cases'!$E$2:$E$106,"*"&$C41&"*",'Test Cases'!$B$2:$B$106,"Cypress (UI)") -> 0 | J41: =COUNTIFS('Test Cases'!$E$2:$E$106,"*"&$C41&"*",'Test Cases'!$B$2:$B$106,"Postman (API)") -> 0 | K41: =COUNTIFS('Test Cases'!$E$2:$E$106,"*"&$C41&"*",'Test Cases'!$B$2:$B$106,"SQL (DB)") -> 3 | L41: =COUNTIFS('Test Cases'!$E$2:$E$106,"*"&$C41&"*",'Test Cases'!$B$2:$B$106,"E2E") -> 4 | M41: =SUM(I41:L41) -> 7 | N41: =IF(M41=0,"NOT COVERED","Covered") -> Covered | O41: =COUNTIFS('Test Cases'!$E$2:$E$106,"*"&$C41&"*",'Test Cases'!$O$2:$O$106,"Pass") -> 0 | P41: =COUNTIFS('Test Cases'!$E$2:$E$106,"*"&$C41&"*",'Test Cases'!$O$2:$O$106,"Fail") -> 0 | Q41: =IF(M41=0,"-",IF(P41>0,"FAIL",IF(O41=M41,"PASS",IF(O41=0,"NOT RUN","IN PROGRESS")))) -> NOT RUN | T41: Cross-layer trace maps + Reconciliation reports

Sheet Coverage Summary
A1: Coverage Analysis & Exit-Criteria Tracker
A2: All figures are formulas reading 'Test Cases' and 'RTM'. Blue text = targets taken from the brief (sections 2.2 and 9.1).
A4: 1. Test counts and pass rate by layer
A5: Layer | C5: Target | D5: Planned | E5: Variance | F5: Passed | G5: Failed | H5: Pass % | I5: Required Pass %
A6: Cypress (UI) | C6: 40 | D6: =COUNTIF('Test Cases'!$B$2:$B$106,A6) -> 40 | E6: =D6-C6 -> 0 | F6: =COUNTIFS('Test Cases'!$B$2:$B$106,A6,'Test Cases'!$O$2:$O$106,"Pass") -> 0 | G6: =COUNTIFS('Test Cases'!$B$2:$B$106,A6,'Test Cases'!$O$2:$O$106,"Fail") -> 0 | H6: =IF(F6+G6=0,"-",F6/(F6+G6)) -> - | I6: 0.9
A7: Postman (API) | C7: 40 | D7: =COUNTIF('Test Cases'!$B$2:$B$106,A7) -> 40 | E7: =D7-C7 -> 0 | F7: =COUNTIFS('Test Cases'!$B$2:$B$106,A7,'Test Cases'!$O$2:$O$106,"Pass") -> 0 | G7: =COUNTIFS('Test Cases'!$B$2:$B$106,A7,'Test Cases'!$O$2:$O$106,"Fail") -> 0 | H7: =IF(F7+G7=0,"-",F7/(F7+G7)) -> - | I7: 1
A8: SQL (DB) | C8: 20 | D8: =COUNTIF('Test Cases'!$B$2:$B$106,A8) -> 20 | E8: =D8-C8 -> 0 | F8: =COUNTIFS('Test Cases'!$B$2:$B$106,A8,'Test Cases'!$O$2:$O$106,"Pass") -> 0 | G8: =COUNTIFS('Test Cases'!$B$2:$B$106,A8,'Test Cases'!$O$2:$O$106,"Fail") -> 0 | H8: =IF(F8+G8=0,"-",F8/(F8+G8)) -> - | I8: 1
A9: E2E | C9: 5 | D9: =COUNTIF('Test Cases'!$B$2:$B$106,A9) -> 5 | E9: =D9-C9 -> 0 | F9: =COUNTIFS('Test Cases'!$B$2:$B$106,A9,'Test Cases'!$O$2:$O$106,"Pass") -> 0 | G9: =COUNTIFS('Test Cases'!$B$2:$B$106,A9,'Test Cases'!$O$2:$O$106,"Fail") -> 0 | H9: =IF(F9+G9=0,"-",F9/(F9+G9)) -> - | I9: 1
A10: Layer tests (UI + API + SQL) | C10: =SUM(C6:C8) -> 100 | D10: =SUM(D6:D8) -> 100 | E10: =D10-C10 -> 0 | F10: =SUM(F6:F8) -> 0 | G10: =SUM(G6:G8) -> 0 | H10: =IF(F10+G10=0,"-",F10/(F10+G10)) -> - | I10: 0.9
A13: 2. Test counts by feature (targets from brief section 2.2)
A14: Feature | B14: Layer | C14: Target | D14: Planned | E14: Variance | F14: Passed | G14: Failed | H14: Pass % | I14: Priority
A15: User Authentication | B15: Cypress (UI) | C15: 4 | D15: =COUNTIFS('Test Cases'!$C$2:$C$106,A15,'Test Cases'!$B$2:$B$106,B15) -> 4 | E15: =D15-C15 -> 0 | F15: =COUNTIFS('Test Cases'!$C$2:$C$106,A15,'Test Cases'!$B$2:$B$106,B15,'Test Cases'!$O$2:$O$106,"Pass") -> 0 | G15: =COUNTIFS('Test Cases'!$C$2:$C$106,A15,'Test Cases'!$B$2:$B$106,B15,'Test Cases'!$O$2:$O$106,"Fail") -> 0 | H15: =IF(F15+G15=0,"-",F15/(F15+G15)) -> - | I15: P0
A16: Order Management | B16: Cypress (UI) | C16: 10 | D16: =COUNTIFS('Test Cases'!$C$2:$C$106,A16,'Test Cases'!$B$2:$B$106,B16) -> 10 | E16: =D16-C16 -> 0 | F16: =COUNTIFS('Test Cases'!$C$2:$C$106,A16,'Test Cases'!$B$2:$B$106,B16,'Test Cases'!$O$2:$O$106,"Pass") -> 0 | G16: =COUNTIFS('Test Cases'!$C$2:$C$106,A16,'Test Cases'!$B$2:$B$106,B16,'Test Cases'!$O$2:$O$106,"Fail") -> 0 | H16: =IF(F16+G16=0,"-",F16/(F16+G16)) -> - | I16: P0
A17: Payment Processing | B17: Cypress (UI) | C17: 6 | D17: =COUNTIFS('Test Cases'!$C$2:$C$106,A17,'Test Cases'!$B$2:$B$106,B17) -> 6 | E17: =D17-C17 -> 0 | F17: =COUNTIFS('Test Cases'!$C$2:$C$106,A17,'Test Cases'!$B$2:$B$106,B17,'Test Cases'!$O$2:$O$106,"Pass") -> 0 | G17: =COUNTIFS('Test Cases'!$C$2:$C$106,A17,'Test Cases'!$B$2:$B$106,B17,'Test Cases'!$O$2:$O$106,"Fail") -> 0 | H17: =IF(F17+G17=0,"-",F17/(F17+G17)) -> - | I17: P0
A18: Delivery Tracking | B18: Cypress (UI) | C18: 6 | D18: =COUNTIFS('Test Cases'!$C$2:$C$106,A18,'Test Cases'!$B$2:$B$106,B18) -> 6 | E18: =D18-C18 -> 0 | F18: =COUNTIFS('Test Cases'!$C$2:$C$106,A18,'Test Cases'!$B$2:$B$106,B18,'Test Cases'!$O$2:$O$106,"Pass") -> 0 | G18: =COUNTIFS('Test Cases'!$C$2:$C$106,A18,'Test Cases'!$B$2:$B$106,B18,'Test Cases'!$O$2:$O$106,"Fail") -> 0 | H18: =IF(F18+G18=0,"-",F18/(F18+G18)) -> - | I18: P0
A19: User Dashboard | B19: Cypress (UI) | C19: 4 | D19: =COUNTIFS('Test Cases'!$C$2:$C$106,A19,'Test Cases'!$B$2:$B$106,B19) -> 4 | E19: =D19-C19 -> 0 | F19: =COUNTIFS('Test Cases'!$C$2:$C$106,A19,'Test Cases'!$B$2:$B$106,B19,'Test Cases'!$O$2:$O$106,"Pass") -> 0 | G19: =COUNTIFS('Test Cases'!$C$2:$C$106,A19,'Test Cases'!$B$2:$B$106,B19,'Test Cases'!$O$2:$O$106,"Fail") -> 0 | H19: =IF(F19+G19=0,"-",F19/(F19+G19)) -> - | I19: P1
A20: Returns & Refunds | B20: Cypress (UI) | C20: 4 | D20: =COUNTIFS('Test Cases'!$C$2:$C$106,A20,'Test Cases'!$B$2:$B$106,B20) -> 4 | E20: =D20-C20 -> 0 | F20: =COUNTIFS('Test Cases'!$C$2:$C$106,A20,'Test Cases'!$B$2:$B$106,B20,'Test Cases'!$O$2:$O$106,"Pass") -> 0 | G20: =COUNTIFS('Test Cases'!$C$2:$C$106,A20,'Test Cases'!$B$2:$B$106,B20,'Test Cases'!$O$2:$O$106,"Fail") -> 0 | H20: =IF(F20+G20=0,"-",F20/(F20+G20)) -> - | I20: P1
A21: Cross-Browser Support | B21: Cypress (UI) | C21: 6 | D21: =COUNTIFS('Test Cases'!$C$2:$C$106,A21,'Test Cases'!$B$2:$B$106,B21) -> 6 | E21: =D21-C21 -> 0 | F21: =COUNTIFS('Test Cases'!$C$2:$C$106,A21,'Test Cases'!$B$2:$B$106,B21,'Test Cases'!$O$2:$O$106,"Pass") -> 0 | G21: =COUNTIFS('Test Cases'!$C$2:$C$106,A21,'Test Cases'!$B$2:$B$106,B21,'Test Cases'!$O$2:$O$106,"Fail") -> 0 | H21: =IF(F21+G21=0,"-",F21/(F21+G21)) -> - | I21: P2
A22: Authentication APIs | B22: Postman (API) | C22: 4 | D22: =COUNTIFS('Test Cases'!$C$2:$C$106,A22,'Test Cases'!$B$2:$B$106,B22) -> 4 | E22: =D22-C22 -> 0 | F22: =COUNTIFS('Test Cases'!$C$2:$C$106,A22,'Test Cases'!$B$2:$B$106,B22,'Test Cases'!$O$2:$O$106,"Pass") -> 0 | G22: =COUNTIFS('Test Cases'!$C$2:$C$106,A22,'Test Cases'!$B$2:$B$106,B22,'Test Cases'!$O$2:$O$106,"Fail") -> 0 | H22: =IF(F22+G22=0,"-",F22/(F22+G22)) -> - | I22: P0
A23: Order APIs | B23: Postman (API) | C23: 10 | D23: =COUNTIFS('Test Cases'!$C$2:$C$106,A23,'Test Cases'!$B$2:$B$106,B23) -> 10 | E23: =D23-C23 -> 0 | F23: =COUNTIFS('Test Cases'!$C$2:$C$106,A23,'Test Cases'!$B$2:$B$106,B23,'Test Cases'!$O$2:$O$106,"Pass") -> 0 | G23: =COUNTIFS('Test Cases'!$C$2:$C$106,A23,'Test Cases'!$B$2:$B$106,B23,'Test Cases'!$O$2:$O$106,"Fail") -> 0 | H23: =IF(F23+G23=0,"-",F23/(F23+G23)) -> - | I23: P0
A24: Payment APIs | B24: Postman (API) | C24: 8 | D24: =COUNTIFS('Test Cases'!$C$2:$C$106,A24,'Test Cases'!$B$2:$B$106,B24) -> 8 | E24: =D24-C24 -> 0 | F24: =COUNTIFS('Test Cases'!$C$2:$C$106,A24,'Test Cases'!$B$2:$B$106,B24,'Test Cases'!$O$2:$O$106,"Pass") -> 0 | G24: =COUNTIFS('Test Cases'!$C$2:$C$106,A24,'Test Cases'!$B$2:$B$106,B24,'Test Cases'!$O$2:$O$106,"Fail") -> 0 | H24: =IF(F24+G24=0,"-",F24/(F24+G24)) -> - | I24: P0
A25: Shipment APIs | B25: Postman (API) | C25: 6 | D25: =COUNTIFS('Test Cases'!$C$2:$C$106,A25,'Test Cases'!$B$2:$B$106,B25) -> 6 | E25: =D25-C25 -> 0 | F25: =COUNTIFS('Test Cases'!$C$2:$C$106,A25,'Test Cases'!$B$2:$B$106,B25,'Test Cases'!$O$2:$O$106,"Pass") -> 0 | G25: =COUNTIFS('Test Cases'!$C$2:$C$106,A25,'Test Cases'!$B$2:$B$106,B25,'Test Cases'!$O$2:$O$106,"Fail") -> 0 | H25: =IF(F25+G25=0,"-",F25/(F25+G25)) -> - | I25: P0
A26: Delivery APIs | B26: Postman (API) | C26: 4 | D26: =COUNTIFS('Test Cases'!$C$2:$C$106,A26,'Test Cases'!$B$2:$B$106,B26) -> 4 | E26: =D26-C26 -> 0 | F26: =COUNTIFS('Test Cases'!$C$2:$C$106,A26,'Test Cases'!$B$2:$B$106,B26,'Test Cases'!$O$2:$O$106,"Pass") -> 0 | G26: =COUNTIFS('Test Cases'!$C$2:$C$106,A26,'Test Cases'!$B$2:$B$106,B26,'Test Cases'!$O$2:$O$106,"Fail") -> 0 | H26: =IF(F26+G26=0,"-",F26/(F26+G26)) -> - | I26: P0
... A33: Audit & Compliance | B33: SQL (DB) | C33: 4 | D33: =COUNTIFS('Test Cases'!$C$2:$C$106,A33,'Test Cases'!$B$2:$B$106,B33) -> 4 | E33: =D33-C33 -> 0 | F33: =COUNTIFS('Test Cases'!$C$2:$C$106,A33,'Test Cases'!$B$2:$B$106,B33,'Test Cases'!$O$2:$O$106,"Pass") -> 0 | G33: =COUNTIFS('Test Cases'!$C$2:$C$106,A33,'Test Cases'!$B$2:$B$106,B33,'Test Cases'!$O$2:$O$106,"Fail") -> 0 | H33: =IF(F33+G33=0,"-",F33/(F33+G33)) -> - | I33: P0
A36: 3. Requirement coverage (RTM)
A37: Functional Requirement | C37: ACs | D37: ACs Covered | E37: Coverage % | F37: Tests Mapped | G37: Passed | H37: Failed
A38: FR-001 User Authentication & Session Management | B38: FR-001 | C38: =COUNTIF(RTM!$A$5:$A$41,B38) -> 7 | D38: =COUNTIFS(RTM!$A$5:$A$41,B38,RTM!$N$5:$N$41,"Covered") -> 7 | E38: =IF(C38=0,0,D38/C38) -> 1 | F38: =SUMIFS(RTM!$M$5:$M$41,RTM!$A$5:$A$41,B38) -> 21 | G38: =SUMIFS(RTM!$O$5:$O$41,RTM!$A$5:$A$41,B38) -> 0 | H38: =SUMIFS(RTM!$P$5:$P$41,RTM!$A$5:$A$41,B38) -> 0
A39: FR-002 Order Management | B39: FR-002 | C39: =COUNTIF(RTM!$A$5:$A$41,B39) -> 7 | D39: =COUNTIFS(RTM!$A$5:$A$41,B39,RTM!$N$5:$N$41,"Covered") -> 7 | E39: =IF(C39=0,0,D39/C39) -> 1 | F39: =SUMIFS(RTM!$M$5:$M$41,RTM!$A$5:$A$41,B39) -> 38 | G39: =SUMIFS(RTM!$O$5:$O$41,RTM!$A$5:$A$41,B39) -> 0 | H39: =SUMIFS(RTM!$P$5:$P$41,RTM!$A$5:$A$41,B39) -> 0
A40: FR-003 Payment Processing | B40: FR-003 | C40: =COUNTIF(RTM!$A$5:$A$41,B40) -> 5 | D40: =COUNTIFS(RTM!$A$5:$A$41,B40,RTM!$N$5:$N$41,"Covered") -> 5 | E40: =IF(C40=0,0,D40/C40) -> 1 | F40: =SUMIFS(RTM!$M$5:$M$41,RTM!$A$5:$A$41,B40) -> 26 | G40: =SUMIFS(RTM!$O$5:$O$41,RTM!$A$5:$A$41,B40) -> 0 | H40: =SUMIFS(RTM!$P$5:$P$41,RTM!$A$5:$A$41,B40) -> 0
A41: FR-004 Shipment & Delivery Tracking | B41: FR-004 | C41: =COUNTIF(RTM!$A$5:$A$41,B41) -> 5 | D41: =COUNTIFS(RTM!$A$5:$A$41,B41,RTM!$N$5:$N$41,"Covered") -> 5 | E41: =IF(C41=0,0,D41/C41) -> 1 | F41: =SUMIFS(RTM!$M$5:$M$41,RTM!$A$5:$A$41,B41) -> 33 | G41: =SUMIFS(RTM!$O$5:$O$41,RTM!$A$5:$A$41,B41) -> 0 | H41: =SUMIFS(RTM!$P$5:$P$41,RTM!$A$5:$A$41,B41) -> 0
A42: FR-005 Returns & Refunds Processing | B42: FR-005 | C42: =COUNTIF(RTM!$A$5:$A$41,B42) -> 5 | D42: =COUNTIFS(RTM!$A$5:$A$41,B42,RTM!$N$5:$N$41,"Covered") -> 5 | E42: =IF(C42=0,0,D42/C42) -> 1 | F42: =SUMIFS(RTM!$M$5:$M$41,RTM!$A$5:$A$41,B42) -> 19 | G42: =SUMIFS(RTM!$O$5:$O$41,RTM!$A$5:$A$41,B42) -> 0 | H42: =SUMIFS(RTM!$P$5:$P$41,RTM!$A$5:$A$41,B42) -> 0
A43: FR-006 Dashboard & Account Management | B43: FR-006 | C43: =COUNTIF(RTM!$A$5:$A$41,B43) -> 4 | D43: =COUNTIFS(RTM!$A$5:$A$41,B43,RTM!$N$5:$N$41,"Covered") -> 4 | E43: =IF(C43=0,0,D43/C43) -> 1 | F43: =SUMIFS(RTM!$M$5:$M$41,RTM!$A$5:$A$41,B43) -> 9 | G43: =SUMIFS(RTM!$O$5:$O$41,RTM!$A$5:$A$41,B43) -> 0 | H43: =SUMIFS(RTM!$P$5:$P$41,RTM!$A$5:$A$41,B43) -> 0
A44: FR-007 Data Consistency & Cross-Layer Validation | B44: FR-007 | C44: =COUNTIF(RTM!$A$5:$A$41,B44) -> 4 | D44: =COUNTIFS(RTM!$A$5:$A$41,B44,RTM!$N$5:$N$41,"Covered") -> 4 | E44: =IF(C44=0,0,D44/C44) -> 1 | F44: =SUMIFS(RTM!$M$5:$M$41,RTM!$A$5:$A$41,B44) -> 22 | G44: =SUMIFS(RTM!$O$5:$O$41,RTM!$A$5:$A$41,B44) -> 0 | H44: =SUMIFS(RTM!$P$5:$P$41,RTM!$A$5:$A$41,B44) -> 0
A45: All requirements | C45: =SUM(C38:C44) -> 37 | D45: =SUM(D38:D44) -> 37 | E45: =IF(C45=0,0,D45/C45) -> 1 | F45: =SUM(F38:F44) -> 168 | G45: =SUM(G38:G44) -> 0 | H45: =SUM(H38:H44) -> 0
A46: Note: 'Tests Mapped' counts a test once per acceptance criterion it covers, so it exceeds the number of test cases.
A49: 4. Exit-criteria check (brief section 9.1)
A50: Criterion | C50: Required | D50: Actual | E50: Status
A51: Cypress UI tests planned | C51: 40 | D51: =D6 -> 40 | E51: =IF(D51>=C51,"Met","Not met") -> Met
A52: Cypress pass rate | C52: 0.9 | D52: =IF(F6+G6=0,0,F6/(F6+G6)) -> 0 | E52: =IF(D52>=C52,"Met","Not met") -> Not met
A53: Postman API tests planned | C53: 40 | D53: =D7 -> 40 | E53: =IF(D53>=C53,"Met","Not met") -> Met
A54: Postman pass rate | C54: 1 | D54: =IF(F7+G7=0,0,F7/(F7+G7)) -> 0 | E54: =IF(D54>=C54,"Met","Not met") -> Not met
A55: SQL validation queries planned | C55: 20 | D55: =D8 -> 20 | E55: =IF(D55>=C55,"Met","Not met") -> Met
A56: SQL pass rate (0 violations) | C56: 1 | D56: =IF(F8+G8=0,0,F8/(F8+G8)) -> 0 | E56: =IF(D56>=C56,"Met","Not met") -> Not met
A57: E2E scenarios planned | C57: 5 | D57: =D9 -> 5 | E57: =IF(D57>=C57,"Met","Not met") -> Met
A58: E2E pass rate | C58: 1 | D58: =IF(F9+G9=0,0,F9/(F9+G9)) -> 0 | E58: =IF(D58>=C58,"Met","Not met") -> Not met
A59: Acceptance criteria covered in RTM | C59: 1 | D59: =E45 -> 1 | E59: =IF(D59>=C59,"Met","Not met") -> Met
A60: Pass-rate rows show 0% until tests have been executed; they will read 'Not met' until results are logged.
